[
  {
    "external_url": "/context/detail/id/169311939/",
    "image_url": "https://cdn1.ozone.ru/s3/multimedia-a/wc250/6010824202.jpg",
    "name": "13.3\" Ноутбук ASUS ZenBook 13 UX331FN-EM039T (90NB0KE2-M01590), серый",
    "price": 58660
  },
  {
    "external_url": "/context/detail/id/200495351/",
    "image_url": "https://cdn1.ozone.ru/s3/multimedia-4/wc250/6024998512.jpg",
    "name": "15.6\" Игровой ноутбук Acer Gaming AN515-54-55Z4 (NH.Q5BER.02Z), черный",
    "price": 81112
  },
  {
    "external_url": "/product/13-3-noutbuk-hp-13-an1018ur-serebristyy-177546359/",
    "image_url": "https://cdn1.ozone.ru/s3/multimedia-4/wc250/6016647628.jpg",
    "name": "13.3\" Ноутбук HP 13-an1018ur, серебристый",
    "price": 54990
  },
  {
    "external_url": "/context/detail/id/201044051/",
    "image_url": "https://cdn1.ozone.ru/s3/multimedia-e/wc250/6025383110.jpg",
    "name": "17.3\" Ноутбук HP 17-ca2036ur (22Q75EA), серебристый",
    "price": 45990
  },
  {
    "external_url": "/product/17-3-noutbuk-msi-gl75-leopard-10scsr-020xru-9s7-17e822-020-chernyy-186643118/",
    "image_url": "https://cdn1.ozone.ru/s3/multimedia-6/wc250/6021040602.jpg",
    "name": "17.3\" Ноутбук MSI GL75 Leopard 10SCSR-020XRU (9S7-17E822-020), черный",
    "price": 76480
  },
  {
    "external_url": "/product/15-6-noutbuk-honor-magicbook-15-r5-512gb-53010ykp-seryy-182829825/",
    "image_url": "https://cdn1.ozone.ru/s3/multimedia-3/wc250/6019667523.jpg",
    "name": "15.6\" Ноутбук Honor MagicBook 15 512GB (53010YKP), серый",
    "price": 52990
  },
  {
    "external_url": "/product/17-3-igrovoy-noutbuk-acer-nitro-5-an517-52-73z0-nh-q80er-008-chernyy-183985419/",
    "image_url": "https://cdn1.ozone.ru/s3/multimedia-1/wc250/6019219141.jpg",
    "name": "17.3\" Игровой ноутбук Acer Nitro 5 AN517-52-73Z0 (NH.Q80ER.008), черный",
    "price": 84890
  },
  {
    "external_url": "/product/14-noutbuk-asus-zenbook-14-um431da-am057-90nb0pb3-m03530-goluboy-195800945/",
    "image_url": "https://cdn1.ozone.ru/s3/multimedia-d/wc250/6022505845.jpg",
    "name": "14\" Ноутбук ASUS Zenbook 14 UM431DA-AM057 (90NB0PB3-M03530), голубой",
    "price": 56200
  },
  {
    "external_url": "/context/detail/id/196287467/",
    "image_url": "https://cdn1.ozone.ru/s3/multimedia-a/wc250/6023064922.jpg",
    "name": "17.3\" Игровой ноутбук ASUS FX705DT-AU027T, черный",
    "price": 79990
  },
  {
    "external_url": "/product/15-6-noutbuk-bravo-15-a4ddr-029ru-9s7-16wk12-029-182537053/",
    "image_url": "https://cdn1.ozone.ru/s3/multimedia-t/wc250/6019823213.jpg",
    "name": "15.6\" Ноутбук MSI Bravo 15 A4DDR-029RU (9S7-16WK12-029), черный",
    "price": 91079
  },
  {
    "external_url": "/context/detail/id/196128594/",
    "image_url": "https://cdn1.ozone.ru/s3/multimedia-u/wc250/6013238238.jpg",
    "name": "14\" Ноутбук Xiaomi Mi RedmiBook (XMA1901-YB) (XMA1901-YB-DOS), серебристый",
    "price": 74655
  },
  {
    "external_url": "/context/detail/id/198108352/",
    "image_url": "https://cdn1.ozone.ru/s3/multimedia-6/wc250/6020738886.jpg",
    "name": "14\" Ноутбук ASUS Zenbook UM425IA (90NB0RT1-M01270) (90NB0RT1-M01270), серый",
    "price": 79990
  },
  {
    "external_url": "/context/detail/id/194227860/",
    "image_url": "https://cdn1.ozone.ru/s3/multimedia-6/wc250/6022812342.jpg",
    "name": "15.6\" Игровой ноутбук MSI GL65 Leopard 10SCSR-051XRU (9S7-16U822-051), черный",
    "price": 78660
  },
  {
    "external_url": "/context/detail/id/148027260/",
    "image_url": "https://cdn1.ozone.ru/s3/multimedia-y/wc250/6008018962.jpg",
    "name": "14\" Ноутбук Lenovo IdeaPad 530S-14IKB (81EU00B7RU), бежевый",
    "price": 50520
  },
  {
    "external_url": "/context/detail/id/201296500/",
    "image_url": "https://cdn1.ozone.ru/s3/multimedia-q/wc250/6025639046.jpg",
    "name": "15.6\" Ноутбук Acer Extensa EX215-51K-50R0 (NX.EFPER.01J), черный",
    "price": 40835
  },
  {
    "external_url": "/product/13-noutbuk-apple-macbook-pro-13-i5-2-0-16gb-1tb-ssd-sg-serebristyy-179329104/",
    "image_url": "https://cdn1.ozone.ru/s3/multimedia-f/wc250/6017707839.jpg",
    "name": "13\" Ноутбук Apple MWP52RU/A, серебристый",
    "price": 187990
  },
  {
    "external_url": "/product/noutbuk-14-1-prestigio-smartbook-141-c4-v-internet-magazine-ozon-tseny-otzyvy-harakteristiki-foto-171584413/",
    "image_url": "https://cdn1.ozone.ru/s3/multimedia-v/wc250/6013160767.jpg",
    "name": "14.1\" Ноутбук Prestigio SmartBook 141 C4 (PSB141C04CGP_DG_CIS), темно-серый",
    "price": 26999
  },
  {
    "external_url": "/context/detail/id/200568783/",
    "image_url": "https://cdn1.ozone.ru/s3/multimedia-q/wc250/6025365482.jpg",
    "name": "14\" Ноутбук Huawei MateBook D 14 NBLL-WDQ9 (53011FQD), серый",
    "price": 59990
  },
  {
    "external_url": "/context/detail/id/198746482/",
    "image_url": "https://cdn1.ozone.ru/s3/multimedia-e/wc250/6023996750.jpg",
    "name": "15.6\" Ноутбук ASUS VivoBook 15 X512FL-BQ441T (90NB0M93-M11210), серый",
    "price": 75000
  },
  {
    "external_url": "/product/15-6-noutbuk-dell-inspiron-3593-3593-8611-3593-8611-serebristyy-181876401/",
    "image_url": "https://cdn1.ozone.ru/s3/multimedia-0/wc250/6016529832.jpg",
    "name": "15.6\" Ноутбук Dell Inspiron 3593 (3593-8611) (3593-8611), серебристый",
    "price": 44511
  },
  {
    "external_url": "/product/noutbuk-asus-fx706ii-au165t-90nr03p1-m02940-seryy-182438946/",
    "image_url": "https://cdn1.ozone.ru/s3/multimedia-k/wc250/6027153848.jpg",
    "name": "17.3\" Ноутбук ASUS FX706II-AU165T (90NR03P1-M02940), серый",
    "price": 74620
  },
  {
    "external_url": "/context/detail/id/160716644/",
    "image_url": "https://cdn1.ozone.ru/s3/multimedia-q/wc250/6014729642.jpg",
    "name": "13\" Ноутбук HP Pavilion 13-an1012ur (8PJ97EA), серебристый",
    "price": 55270
  },
  {
    "external_url": "/product/noutbuk-dell-g3-15-3590-g315-8480-belyy-182424172/",
    "image_url": "https://cdn1.ozone.ru/s3/multimedia-f/wc250/6019453047.jpg",
    "name": "15.6\" Игровой ноутбук Dell G3 15-3590 (G315-8480), белый",
    "price": 97910
  },
  {
    "external_url": "/context/detail/id/200522123/",
    "image_url": "https://cdn1.ozone.ru/s3/multimedia-l/wc250/6025021893.jpg",
    "name": "15.6\" Ноутбук Huawei MateBook D 15 BOHL-WDQ9 (53011FPK), серый",
    "price": 59990
  },
  {
    "external_url": "/product/15-6-noutbuk-acer-conceptd-7-pro-cn715-71p-70xb-nx-c4per-001-belyy-189479802/",
    "image_url": "https://cdn1.ozone.ru/s3/multimedia-w/wc250/6021304112.jpg",
    "name": "15.6\" Ноутбук Acer ConceptD 7 Pro CN715-71P-70XB (NX.C4PER.001), белый",
    "price": 369990
  },
  {
    "external_url": "/product/15-6-noutbuk-acer-aspire-3-a315-42-r8gl-nx-hf9er-02h-chernyy-179664425/",
    "image_url": "https://cdn1.ozone.ru/s3/multimedia-y/wc250/6027153754.jpg",
    "name": "15.6\" Ноутбук Acer Aspire 3 A315-42-R8GL (NX.HF9ER.02H), черный",
    "price": 54200
  },
  {
    "external_url": "/context/detail/id/199868709/",
    "image_url": "https://cdn1.ozone.ru/s3/multimedia-q/wc250/6027153998.jpg",
    "name": "14\" Ноутбук HP 14s-fq0028ur (22P64EA), серый",
    "price": 41560
  },
  {
    "external_url": "/context/detail/id/201065507/",
    "image_url": "https://cdn1.ozone.ru/s3/multimedia-r/wc250/6004664439.jpg",
    "name": "15.6\" Ноутбук ASUS ZenBook 15 UX534FTC-AA061T (90NB0NK3-M03690), синий",
    "price": 114499
  },
  {
    "external_url": "/product/15-6-igrovoy-noutbuk-lenovo-ideapad-gaming-3-15arh05-82ey0022ru-siniy-189121246/",
    "image_url": "https://cdn1.ozone.ru/s3/multimedia-u/wc250/6027746562.jpg",
    "name": "15.6\" Игровой ноутбук Lenovo IdeaPad Gaming 3 15ARH05 (82EY0022RU), синий",
    "price": 71890
  },
  {
    "external_url": "/context/detail/id/199384377/",
    "image_url": "https://cdn1.ozone.ru/s3/multimedia-d/wc250/6024351313.jpg",
    "name": "15.6\" Ноутбук Dell Vostro 3590-7605 (3590-7605), темно-серый",
    "price": 46060
  },
  {
    "external_url": "/context/detail/id/201296506/",
    "image_url": "https://cdn1.ozone.ru/s3/multimedia-5/wc250/6025639061.jpg",
    "name": "15.6\" Ноутбук Lenovo V15-ADA (82C7000YRU), серый",
    "price": 45719
  },
  {
    "external_url": "/product/17-3-igrovoy-noutbuk-msi-gs75-stealth-10sfs-402ru-9s7-17g311-402-chernyy-191286386/",
    "image_url": "https://cdn1.ozone.ru/s3/multimedia-5/wc250/6019385033.jpg",
    "name": "17.3\" Игровой ноутбук MSI GS75 Stealth 10SFS-402RU (9S7-17G311-402), черный",
    "price": 236590
  },
  {
    "external_url": "/context/detail/id/201067043/",
    "image_url": "https://cdn1.ozone.ru/s3/multimedia-9/wc250/6027153837.jpg",
    "name": "15.6\" Ноутбук ASUS VivoBook M570DD-DM057 (90NB0PK1-M02500), черный",
    "price": 62499
  },
  {
    "external_url": "/product/13-3-noutbuk-asus-zenbook-13-ux331fn-em060t-90nb0ke2-m01610-seryy-175411128/",
    "image_url": "https://cdn1.ozone.ru/s3/multimedia-a/wc250/6010824202.jpg",
    "name": "13.3\" Ноутбук ASUS ZenBook 13 UX331FN-EM060T (90NB0KE2-M01610), серый",
    "price": 66000
  },
  {
    "external_url": "/context/detail/id/160366965/",
    "image_url": "https://cdn1.ozone.ru/multimedia/wc250/1028561264.jpg",
    "name": "15.6\" Ноутбук Lenovo (81FB004DRU), серый",
    "price": 45785
  },
  {
    "external_url": "/context/detail/id/194032943/",
    "image_url": "https://cdn1.ozone.ru/s3/multimedia-8/wc250/6022519556.jpg",
    "name": "15.6\" Ноутбук ASUS VivoBook 15 X512FL-BQ830T (90NB0M97-M11190), черный, коралловый",
    "price": 63500
  },
  {
    "external_url": "/context/detail/id/195487711/",
    "image_url": "https://cdn1.ozone.ru/s3/multimedia-2/wc250/6023072690.jpg",
    "name": "14\" Ноутбук HP Pavilion x360 14-dh0049ur 1U2W4EA (71558807), серебристый",
    "price": 45990
  },
  {
    "external_url": "/context/detail/id/201296501/",
    "image_url": "https://cdn1.ozone.ru/s3/multimedia-p/wc250/6025639009.jpg",
    "name": "15.6\" Ноутбук Acer Aspire A315-23-R2KW (NX.HVTER.018), черный",
    "price": 41372
  },
  {
    "external_url": "/context/detail/id/160714552/",
    "image_url": "https://cdn1.ozone.ru/s3/multimedia-o/wc250/6004664616.jpg",
    "name": "15.6\" Ноутбук Dell Inspiron 3593 (3593-7903), черный",
    "price": 43410
  },
  {
    "external_url": "/context/detail/id/193991545/",
    "image_url": "https://cdn1.ozone.ru/s3/multimedia-m/wc250/6022727830.jpg",
    "name": "15.6\" Ноутбук Dell Vostro 3591 (3591-6302), черный",
    "price": 45590
  },
  {
    "external_url": "/product/14-noutbuk-acer-travelmate-p2-tmp214-52-3763-nx-vlher-00h-chernyy-194375638/",
    "image_url": "https://cdn1.ozone.ru/s3/multimedia-3/wc250/6022861731.jpg",
    "name": "14\" Ноутбук Acer TravelMate P2 TMP214-52-3763 (NX.VLHER.00H), черный",
    "price": 39920
  },
  {
    "external_url": "/product/13-3-noutbuk-apple-air13-seryy-176662447/",
    "image_url": "https://cdn1.ozone.ru/s3/multimedia-l/wc250/6013995849.jpg",
    "name": "13\" Ноутбук Apple Macbook Air (MVH22RU/A), серый",
    "price": 119990
  },
  {
    "external_url": "/context/detail/id/201036292/",
    "image_url": "https://cdn1.ozone.ru/s3/multimedia-w/wc250/6019448492.jpg",
    "name": "14\" Ноутбук ASUS Zenbook UX431FA-AM196T (90NB0MB3-M05830), голубой",
    "price": 52990
  },
  {
    "external_url": "/product/13-3-noutbuk-asus-zenbook-ux325ja-eg109t-90nb0qy1-m01750-seryy-183391251/",
    "image_url": "https://cdn1.ozone.ru/s3/multimedia-x/wc250/6019645701.jpg",
    "name": "13.3\" Ноутбук ASUS ZenBook UX325JA-EG109T (90NB0QY1-M01750), серый",
    "price": 67340
  },
  {
    "external_url": "/context/detail/id/194186341/",
    "image_url": "https://cdn1.ozone.ru/s3/multimedia-w/wc250/6027002696.jpg",
    "name": "15.6\" Ноутбук ASUS Pro P2540FA-DM0282 (90NX02L1-M03500), черный",
    "price": 46552
  },
  {
    "external_url": "/product/noutbuk-13-3-apple-nou2-11-v-internet-magazine-ozon-tseny-otzyvy-harakteristiki-foto-174585260/",
    "image_url": "https://cdn1.ozone.ru/s3/multimedia-b/wc250/6014631419.jpg",
    "name": "13.3\" Ноутбук Apple NOU2-11, серебристый",
    "price": 71990
  },
  {
    "external_url": "/product/15-6-noutbuk-hp-15-db1209ur-s-104g5ea-chernyy-182438973/",
    "image_url": "https://cdn1.ozone.ru/s3/multimedia-v/wc250/6027153859.jpg",
    "name": "15.6\" Ноутбук HP 15-db1209ur/s (104G5EA), черный",
    "price": 48020
  },
  {
    "external_url": "/context/detail/id/202236727/",
    "image_url": "https://cdn1.ozone.ru/s3/multimedia-6/wc250/6026202678.jpg",
    "name": "15.6\" Ноутбук Xiaomi Mi Notebook Pro (JYU4159CN), серый",
    "price": 74459
  },
  {
    "external_url": "/context/detail/id/200521641/",
    "image_url": "https://cdn1.ozone.ru/s3/multimedia-p/wc250/6019452913.jpg",
    "name": "13\" Ноутбук Apple MacBook Pro 13 (MWP72RU/A), серебристый",
    "price": 173990
  },
  {
    "external_url": "/context/detail/id/201067232/",
    "image_url": "https://cdn1.ozone.ru/s3/multimedia-5/wc250/6027153833.jpg",
    "name": "15.6\" Ноутбук ASUS M570DD-DM009 (90NB0PK1-M02480), черный",
    "price": 57999
  },
  {
    "external_url": "/context/detail/id/194237845/",
    "image_url": "https://cdn1.ozone.ru/s3/multimedia-z/wc250/6015288083.jpg",
    "name": "15.6\" Ноутбук Acer Aspire A315-42G-R86E (NX.HF8ER.02S), черный",
    "price": 57999
  },
  {
    "external_url": "/product/noutbuk-asus-m570dd-dm009-90nb0pk1-m02480-chernyy-182201459/",
    "image_url": "https://cdn1.ozone.ru/s3/multimedia-5/wc250/6027153833.jpg",
    "name": "15.6\" Ноутбук ASUS M570DD-DM009 (90NB0PK1-M02480), черный",
    "price": 60310
  },
  {
    "external_url": "/context/detail/id/198943353/",
    "image_url": "https://cdn1.ozone.ru/s3/multimedia-b/wc250/6024250367.jpg",
    "name": "14\" Ноутбук HP 14s-fq0032ur (22M94EA) (22M94EA), белый",
    "price": 50286
  },
  {
    "external_url": "/context/detail/id/199384372/",
    "image_url": "https://cdn1.ozone.ru/s3/multimedia-7/wc250/6010762027.jpg",
    "name": "15.6\" Ноутбук HP 255 G7 (15S50ES) (15S50ES), серебристый",
    "price": 44149
  },
  {
    "external_url": "/product/14-noutbuk-asus-vivobook-14-k413fa-eb527t-90nb0q0b-m07900-serebristyy-201067245/",
    "image_url": "https://cdn1.ozone.ru/s3/multimedia-6/wc250/6027968442.jpg",
    "name": "14\" Ноутбук ASUS VivoBook 14 K413FA-EB527T (90NB0Q0B-M07900), серебристый",
    "price": 47599
  },
  {
    "external_url": "/product/15-6-igrovoy-noutbuk-acer-nitro-5-an515-55-779u-nh-q7qer-008-chernyy-182526704/",
    "image_url": "https://cdn1.ozone.ru/s3/multimedia-h/wc250/6019254473.jpg",
    "name": "15.6\" Игровой ноутбук Acer Nitro 5 AN515-55-779U (NH.Q7QER.008), черный",
    "price": 110990
  },
  {
    "external_url": "/context/detail/id/168451105/",
    "image_url": "https://cdn1.ozone.ru/s3/multimedia-w/wc250/6009152312.jpg",
    "name": "15.6\" Ноутбук Acer Extensa 15 EX215-51G-59CT (NX.EG1ER.00K), черный",
    "price": 56990
  },
  {
    "external_url": "/context/detail/id/194809831/",
    "image_url": "https://cdn1.ozone.ru/s3/multimedia-8/wc250/6022973192.jpg",
    "name": "14\" Ноутбук ASUS K413FA (EB407) (K413FA-EB407), черный",
    "price": 45864
  },
  {
    "external_url": "/product/noutbuk-ideapad-ip5-15iil05-81yk001gru-175413787/",
    "image_url": "https://cdn1.ozone.ru/s3/multimedia-z/wc250/6015267023.jpg",
    "name": "15.6\" Ноутбук Lenovo IdeaPad IP5 15IIL05 (81YK001GRU), бирюзовый",
    "price": 59010
  },
  {
    "external_url": "/context/detail/id/193991570/",
    "image_url": "https://cdn1.ozone.ru/s3/multimedia-c/wc250/6022727820.jpg",
    "name": "15.6\" Ноутбук Acer Extensa EX215-51-55L6 (NX.EFZER.013), черный",
    "price": 44100
  },
  {
    "external_url": "/product/14-noutbuk-acer-swift-3-sf314-41-r4c4-nx-hfder-004-serebristyy-184123225/",
    "image_url": "https://cdn1.ozone.ru/s3/multimedia-a/wc250/6019692478.jpg",
    "name": "14\" Ноутбук Acer Swift 3 SF314-41-R4C4 (NX.HFDER.004), серебристый",
    "price": 35990
  },
  {
    "external_url": "/context/detail/id/201815373/",
    "image_url": "https://cdn1.ozone.ru/s3/multimedia-v/wc250/6025904875.jpg",
    "name": "15.6\" Ноутбук Acer Aspire 3 A315-42-R7KG (NX.HF9ER.034), черный",
    "price": 60963
  },
  {
    "external_url": "/context/detail/id/199384384/",
    "image_url": "https://cdn1.ozone.ru/s3/multimedia-9/wc250/6027172341.jpg",
    "name": "15.6\" Ноутбук HP 15s-eq0053ur (22R17EA), серебристый",
    "price": 43610
  },
  {
    "external_url": "/product/17-3-noutbuk-acer-conceptd-9-cn917-71-964c-nx-c4ler-003-chernyy-189588039/",
    "image_url": "https://cdn1.ozone.ru/s3/multimedia-4/wc250/6021304300.jpg",
    "name": "17.3\" Ноутбук Acer ConceptD 9 CN917-71-964C (NX.C4LER.003), черный",
    "price": 469990
  },
  {
    "external_url": "/context/detail/id/202469036/",
    "image_url": "https://cdn1.ozone.ru/s3/multimedia-t/wc250/6026669621.jpg",
    "name": "15.6\" Ноутбук Acer Extensa 15 EX215-22-R06J (NX.EG9ER.012), черный",
    "price": 40076
  },
  {
    "external_url": "/context/detail/id/160716641/",
    "image_url": "https://cdn1.ozone.ru/s3/multimedia-9/wc250/6004379157.jpg",
    "name": "13\" Ноутбук HP Pavilion 13-an1011ur (8PJ98EA), серебристый",
    "price": 47202
  },
  {
    "external_url": "/context/detail/id/203465844/",
    "image_url": "https://cdn1.ozone.ru/s3/multimedia-l/wc250/6027233949.jpg",
    "name": "16.1\" Ноутбук Xiaomi. RedmiBook (XMA2012-DB), серый",
    "price": 72980
  },
  {
    "external_url": "/context/detail/id/193991578/",
    "image_url": "https://cdn1.ozone.ru/s3/multimedia-k/wc250/6022727792.jpg",
    "name": "17.3\" Ноутбук Lenovo IdeaPad 3 17IML05 (81WC000JRU), синий, серый",
    "price": 44890
  },
  {
    "external_url": "/product/14-noutbuk-acer-swift-3-sf314-41-r663-nx-hfeer-001-siniy-184132109/",
    "image_url": "https://cdn1.ozone.ru/s3/multimedia-e/wc250/6027744854.jpg",
    "name": "14\" Ноутбук Acer Swift 3 SF314-41-R663 (NX.HFEER.001), синий",
    "price": 36290
  },
  {
    "external_url": "/product/noutbuk-hp-15s-dw2024ur-s-104k6ea-chernyy-182438977/",
    "image_url": "https://cdn1.ozone.ru/s3/multimedia-m/wc250/6019730542.jpg",
    "name": "15.6\" Ноутбук HP 15s-dw2024ur/s (104K6EA), черный",
    "price": 41810
  },
  {
    "external_url": "/context/detail/id/203969095/",
    "image_url": "https://cdn1.ozone.ru/s3/multimedia-4/wc250/6024250072.jpg",
    "name": "15.6\" Ноутбук Acer A315-42-R9G5 (147), черный",
    "price": 38990
  },
  {
    "external_url": "/product/14-noutbuk-xiaomi-mi-redmibook-xma1901-da-xma1901-da-serebristyy-176750793/",
    "image_url": "https://cdn1.ozone.ru/s3/multimedia-o/wc250/6013654464.jpg",
    "name": "14\" Ноутбук Xiaomi Mi RedmiBook XMA1901-DA (XMA1901-DA), серебристый",
    "price": 66990
  },
  {
    "external_url": "/product/noutbuk-14-huawei-matebook-d-14-nbl-waq9r-v-internet-magazine-ozon-tseny-otzyvy-harakteristiki-foto-172305452/",
    "image_url": "https://cdn1.ozone.ru/s3/multimedia-4/wc250/6027153796.jpg",
    "name": "14\" Ноутбук Huawei Matebook D 14 R5 512GB (53010TTB), серый",
    "price": 45948
  },
  {
    "external_url": "/context/detail/id/192792150/",
    "image_url": "https://cdn1.ozone.ru/s3/multimedia-p/wd250/6022290217.jpg",
    "name": "15.6\" Ноутбук Acer PT515-52-75HU (NH.Q6WER.005), черный",
    "price": 216990
  },
  {
    "external_url": "/product/noutbuk-14-honor-magicbook-14-v-internet-magazine-ozon-tseny-otzyvy-harakteristiki-foto-171455020/",
    "image_url": "https://cdn1.ozone.ru/s3/multimedia-o/wc250/6009814920.jpg",
    "name": "14\" Ноутбук Honor MagicBook 14 R5 512GB (53010VTY), серый",
    "price": 52990
  },
  {
    "external_url": "/product/13-3-noutbuk-haier-a914-td0030550ru-chernyy-182537031/",
    "image_url": "https://cdn1.ozone.ru/s3/multimedia-x/wc250/6019822713.jpg",
    "name": "13.3\" Ноутбук Haier A914 (TD0030550RU), черный",
    "price": 24990
  },
  {
    "external_url": "/context/detail/id/166421197/",
    "image_url": "https://cdn1.ozone.ru/s3/multimedia-p/wc250/6027153781.jpg",
    "name": "16.1\" Ноутбук Honor MagicBook Pro 512GB (53010TSA), серый",
    "price": 59990
  },
  {
    "external_url": "/context/detail/id/201816375/",
    "image_url": "https://cdn1.ozone.ru/s3/multimedia-j/wc250/6025907275.jpg",
    "name": "17.3\" Ноутбук ASUS VivoBook D712DA-AU280 (90NB0PI3-M04410), серебристый",
    "price": 46853
  },
  {
    "external_url": "/context/detail/id/160682759/",
    "image_url": "https://cdn1.ozone.ru/s3/multimedia-s/wc250/6027153748.jpg",
    "name": "15.6\" Игровой ноутбук ASUS TUF Gaming FX505DT-BQ138T (90NR02D1-M07160), темно-серый",
    "price": 70502
  },
  {
    "external_url": "/context/detail/id/201042733/",
    "image_url": "https://cdn1.ozone.ru/s3/multimedia-f/wc250/6025372311.jpg",
    "name": "13.3\" Ноутбук Irbis NB500, серебристый",
    "price": 19990
  },
  {
    "external_url": "/product/15-6-noutbuk-lenovo-v130-15ikb-81hn0113ru-seryy-182439043/",
    "image_url": "https://cdn1.ozone.ru/s3/multimedia-y/wc250/6019821526.jpg",
    "name": "15.6\" Ноутбук Lenovo V130-15IKB (81HN0113RU), серый",
    "price": 38909
  },
  {
    "external_url": "/context/detail/id/163228324/",
    "image_url": "https://cdn1.ozone.ru/s3/multimedia-4/wc250/6006537352.jpg",
    "name": "15.6\" Ноутбук Acer Extensa 15 EX215-51-59L4 (NX.EFZER.007), черный",
    "price": 40990
  },
  {
    "external_url": "/product/15-6-noutbuk-alienware-m15-7526-seryy-185104349/",
    "image_url": "https://cdn1.ozone.ru/s3/multimedia-q/wd250/6020186918.jpg",
    "name": "15.6\" Ноутбук Alienware M15-7526, серый",
    "price": 244990
  },
  {
    "external_url": "/product/noutbuk-lenovo-v130-15ikb-81hn011bru-seryy-182439045/",
    "image_url": "https://cdn1.ozone.ru/s3/multimedia-y/wc250/6019821526.jpg",
    "name": "15.6\" Ноутбук Lenovo V130-15IKB (81HN011BRU), серый",
    "price": 38627
  },
  {
    "external_url": "/product/13-noutbuk-apple-macbook-pro-13-i5-2-0-16gb-1tb-ssd-sil-serebristyy-179329106/",
    "image_url": "https://cdn1.ozone.ru/s3/multimedia-p/wc250/6019452913.jpg",
    "name": "13\" Ноутбук Apple MacBook Pro 13 (MWP82RU/A), серебристый",
    "price": 187990
  },
  {
    "external_url": "/product/15-6-igrovoy-noutbuk-msi-gf63-thin-9rcx-868xru-9s7-16r312-868-chernyy-175652628/",
    "image_url": "https://cdn1.ozone.ru/s3/multimedia-s/wc250/6006515992.jpg",
    "name": "15.6\" Ноутбук MSI GF63 Thin 9RCX-868XRU (9S7-16R312-868), черный",
    "price": 63500
  },
  {
    "external_url": "/product/13-3-noutbuk-panasonic-toughbook-cf-31mk5-2-cf-314b503n9-seryy-186536107/",
    "image_url": "https://cdn1.ozone.ru/s3/multimedia-a/wc250/6020605294.jpg",
    "name": "13.1\" Ноутбук Panasonic Toughbook CF-31mk5 (CF-314B503N9), серый",
    "price": 343990
  },
  {
    "external_url": "/context/detail/id/201044062/",
    "image_url": "https://cdn1.ozone.ru/s3/multimedia-7/wc250/6025383283.jpg",
    "name": "15.6\" Ноутбук Acer Aspire A315-42-R6N1 (NX.HF9ER.041), черный",
    "price": 40990
  },
  {
    "external_url": "/product/13-noutbuk-huawei-matebook-13-hn-w19r-seryy-182536664/",
    "image_url": "https://cdn1.ozone.ru/s3/multimedia-j/wc250/6027153811.jpg",
    "name": "13\" Ноутбук Huawei MateBook 13 R5 (53011AAX), серый",
    "price": 59990
  },
  {
    "external_url": "/context/detail/id/200568505/",
    "image_url": "https://cdn1.ozone.ru/s3/multimedia-p/wd250/6016362745.jpg",
    "name": "15.6\" Ноутбук Lenovo Legion 7i 15IMHg05 (81YU0014RK) (81YU0014RK), серый",
    "price": 289990
  },
  {
    "external_url": "/product/15-6-noutbuk-hp-255-g7-2d232ea-serebristyy-182535911/",
    "image_url": "https://cdn1.ozone.ru/s3/multimedia-n/wc250/6027153887.jpg",
    "name": "15.6\" Ноутбук HP 255 G7 (2D232EA), серебристый",
    "price": 41990
  },
  {
    "external_url": "/product/15-6-noutbuk-acer-conceptd-7-ezel-pro-cc715-91p-x7v8-nx-c5fer-001-belyy-191015548/",
    "image_url": "https://cdn1.ozone.ru/s3/multimedia-b/wc250/6021632195.jpg",
    "name": "15.6\" Ноутбук Acer ConceptD 7 Ezel Pro CC715-91P-X7V8 (NX.C5FER.001), белый",
    "price": 479990
  },
  {
    "external_url": "/product/15-6-noutbuk-dell-alienware-m15-alienware-m15-7502-seryy-192729832/",
    "image_url": "https://cdn1.ozone.ru/s3/multimedia-q/wd250/6020186918.jpg",
    "name": "15.6\" Ноутбук Dell Alienware M15 (Alienware M15-7502), серый",
    "price": 219990
  },
  {
    "external_url": "/context/detail/id/200552446/",
    "image_url": "https://cdn1.ozone.ru/s3/multimedia-w/wc250/6024930932.jpg",
    "name": "15.6\" Ноутбук ASUS X540UA-DM3218T, черный",
    "price": 35990
  },
  {
    "external_url": "/product/14-noutbuk-acer-swift-3-sf314-41-r663-nx-hfeer-001-siniy-184123224/",
    "image_url": "https://cdn1.ozone.ru/s3/multimedia-e/wc250/6027744854.jpg",
    "name": "14\" Ноутбук Acer Swift 3 SF314-41-R663 (NX.HFEER.001), синий",
    "price": 35990
  },
  {
    "external_url": "/product/noutbuk-acer-ex215-51kg-56vn-nx-efqer-00q-chernyy-182449776/",
    "image_url": "https://cdn1.ozone.ru/s3/multimedia-u/wc250/6005192814.jpg",
    "name": "15.6\" Ноутбук Acer EX215-51KG-56VN (NX.EFQER.00Q), черный",
    "price": 44990
  },
  {
    "external_url": "/context/detail/id/197006819/",
    "image_url": "https://cdn1.ozone.ru/s3/multimedia-d/wc250/6022505845.jpg",
    "name": "14\" Ноутбук ASUS ZenBook UM431DA (90NB0PB3-M03550) (90NB0PB3-M03550), голубой",
    "price": 60300
  },
  {
    "external_url": "/context/detail/id/201035683/",
    "image_url": "https://cdn1.ozone.ru/s3/multimedia-a/wc250/6025364602.jpg",
    "name": "17.3\" Игровой ноутбук ASUS TUF Gaming A17 FX706II-H7032 (90NR03P1-M03180), серый",
    "price": 79990
  },
  {
    "external_url": "/product/noutbuk-lenovo-thinkbook-14-iil-20sl003nru-seryy-182449816/",
    "image_url": "https://cdn1.ozone.ru/s3/multimedia-a/wc250/6010274878.jpg",
    "name": "14\" Ноутбук Lenovo ThinkBook 14 IIL (20SL003NRU), серый",
    "price": 40150
  },
  {
    "external_url": "/product/noutbuk-14-asus-zenbook-14-um431da-am010t-v-internet-magazine-ozon-tseny-otzyvy-harakteristiki-foto-172477716/",
    "image_url": "https://cdn1.ozone.ru/s3/multimedia-t/wc250/6027153749.jpg",
    "name": "14\" Ноутбук ASUS ZenBook 14 UM431DA-AM010T (90NB0PB3-M01440), серебристый",
    "price": 53490
  },
  {
    "external_url": "/context/detail/id/201296497/",
    "image_url": "https://cdn1.ozone.ru/s3/multimedia-j/wc250/6025639003.jpg",
    "name": "15.6\" Ноутбук HP 250 G7 (8MJ03EA), темно-серый",
    "price": 35462
  },
  {
    "external_url": "/context/detail/id/203070924/",
    "image_url": "https://cdn1.ozone.ru/s3/multimedia-q/wd250/6022290398.jpg",
    "name": "15.6\" Игровой ноутбук Lenovo 81YU0011RK (30051285), серый",
    "price": 251490
  },
  {
    "external_url": "/context/detail/id/200529427/",
    "image_url": "https://cdn1.ozone.ru/s3/multimedia-w/wc250/6024930932.jpg",
    "name": "15.6\" Ноутбук ASUS VivoBook  X540UA-DM3187, черный",
    "price": 41999
  },
  {
    "external_url": "/context/detail/id/201067337/",
    "image_url": "https://cdn1.ozone.ru/s3/multimedia-4/wc250/6027153796.jpg",
    "name": "14\" Ноутбук Huawei Matebook D 14 R5 512GB (53010TTB), серый",
    "price": 48499
  },
  {
    "external_url": "/context/detail/id/202469100/",
    "image_url": "https://cdn1.ozone.ru/s3/multimedia-g/wc250/6026669428.jpg",
    "name": "15.6\" Ноутбук Acer Extensa 15 EX215-52-312N (NX.EG8ER.01M), черный",
    "price": 38869
  },
  {
    "external_url": "/product/14-noutbuk-asus-vivobook-m433ia-eb400t-90nb0qr4-m06050-chernyy-190424680/",
    "image_url": "https://cdn1.ozone.ru/s3/multimedia-9/wc250/6027153909.jpg",
    "name": "14\" Ноутбук ASUS VivoBook M433IA-EB400T (90NB0QR4-M06050), черный",
    "price": 47990
  },
  {
    "external_url": "/product/noutbuk-msi-gl65-10scsr-017ru-9s7-16u822-017-chernyy-175414780/",
    "image_url": "https://cdn1.ozone.ru/s3/multimedia-p/wc250/6015294193.jpg",
    "name": "15.6\" Ноутбук MSI GL65 10SCSR-017RU (9S7-16U822-017), черный",
    "price": 87990
  },
  {
    "external_url": "/context/detail/id/200522099/",
    "image_url": "https://cdn1.ozone.ru/s3/multimedia-j/wc250/6025021891.jpg",
    "name": "14\" Ноутбук HP 14s-fq0006ur 1U2X6EA, серебристый",
    "price": 46990
  },
  {
    "external_url": "/context/detail/id/201067349/",
    "image_url": "https://cdn1.ozone.ru/s3/multimedia-g/wc250/6019453156.jpg",
    "name": "14\" Ноутбук ASUS K413FA-EB526T (90NB0Q0G-M07890), золотой",
    "price": 47699
  },
  {
    "external_url": "/product/15-6-igrovoy-noutbuk-lenovo-legion-5-15arh05-82b500ghrk-chernyy-191050133/",
    "image_url": "https://cdn1.ozone.ru/s3/multimedia-u/wc250/6027746526.jpg",
    "name": "15.6\" Игровой ноутбук Lenovo Legion 5 15ARH05 (82B500GHRK), черный",
    "price": 86090
  },
  {
    "external_url": "/product/14-noutbuk-acer-aspire-5-a514-53-78ue-nx-huser-002-serebristyy-182526715/",
    "image_url": "https://cdn1.ozone.ru/s3/multimedia-f/wc250/6019238955.jpg",
    "name": "14\" Ноутбук Acer Aspire 5 A514-53-78UE (NX.HUSER.002), серебристый",
    "price": 59990
  },
  {
    "external_url": "/context/detail/id/195801010/",
    "image_url": "https://cdn1.ozone.ru/s3/multimedia-w/wc250/6019645772.jpg",
    "name": "14\" Ноутбук ASUS ZenBook UX434FQ-A6073T (90NB0RM1-M00970), синий",
    "price": 106800
  },
  {
    "external_url": "/context/detail/id/201815388/",
    "image_url": "https://cdn1.ozone.ru/s3/multimedia-q/wc250/6025904942.jpg",
    "name": "15.6\" Игровой ноутбук HP Pavilion Gaming 15-ec0060ur (22N65EA), черный",
    "price": 61135
  },
  {
    "external_url": "/context/detail/id/160716317/",
    "image_url": "https://cdn1.ozone.ru/s3/multimedia-u/wc250/6027153750.jpg",
    "name": "15.6\" Ноутбук Acer Aspire 3 A315-42G-R9XV (NX.HF8ER.02D), черный",
    "price": 48990
  },
  {
    "external_url": "/product/noutbuk-honor-magicbook-14-nbll-wdq9hn-53011fgr-seryy-191544396/",
    "image_url": "https://cdn1.ozone.ru/s3/multimedia-q/wc250/6027153926.jpg",
    "name": "14\" Ноутбук Honor MagicBook 14 NblL-WDQ9HN (53011FGR), серый",
    "price": 59990
  },
  {
    "external_url": "/context/detail/id/166303243/",
    "image_url": "https://cdn1.ozone.ru/s3/multimedia-p/wc250/6004771321.jpg",
    "name": "14\" Ноутбук Dell Wyse X90M7  (X90M7/8/240), черный",
    "price": 34500
  },
  {
    "external_url": "/context/detail/id/199402688/",
    "image_url": "https://cdn1.ozone.ru/s3/multimedia-1/wc250/6025150753.jpg",
    "name": "14\" Ноутбук ASUS PRO P1440FA-FA2025T (90NX0211-M30020), серый",
    "price": 39310
  },
  {
    "external_url": "/context/detail/id/202784945/",
    "image_url": "https://cdn1.ozone.ru/s3/multimedia-v/wc250/6027441391.jpg",
    "name": "15.6\" Ноутбук Acer A315-42-R9RD (126), красный",
    "price": 42990
  },
  {
    "external_url": "/product/noutbuk-lenovo-ip-3-15ada05-81w1004uru-platinovyy-seryy-182449830/",
    "image_url": "https://cdn1.ozone.ru/s3/multimedia-i/wc250/6027153882.jpg",
    "name": "15.6\" Ноутбук Lenovo IdeaPad 3 15ADA05 (81W1004URU), платиновый серый",
    "price": 39590
  },
  {
    "external_url": "/product/15-6-noutbuk-acer-aspire-a315-42-r4h1-nx-hf9er-04a-chernyy-193991549/",
    "image_url": "https://cdn1.ozone.ru/s3/multimedia-t/wc250/6027153929.jpg",
    "name": "15.6\" Ноутбук Acer Aspire A315-42-R4H1 (NX.HF9ER.04A), черный",
    "price": 44190
  },
  {
    "external_url": "/context/detail/id/198796992/",
    "image_url": "https://cdn1.ozone.ru/s3/multimedia-w/wc250/6024158408.jpg",
    "name": "17.3\" Ноутбук Lenovo IP 3 17ARE05 (81W5002DRK), серый",
    "price": 51520
  },
  {
    "external_url": "/product/14-noutbuk-msi-modern-14-b10mw-023xru-9s7-14d111-023-chernyy-182537680/",
    "image_url": "https://cdn1.ozone.ru/s3/multimedia-0/wc250/6019386288.jpg",
    "name": "14\" Ноутбук MSI Modern 14 B10MW-023XRU (9S7-14D111-023), черный",
    "price": 55230
  },
  {
    "external_url": "/context/detail/id/193944159/",
    "image_url": "https://cdn1.ozone.ru/s3/multimedia-6/wc250/6022674894.jpg",
    "name": "13\" Ноутбук Apple MacBook Pro 13 , серебристый",
    "price": 132990
  },
  {
    "external_url": "/context/detail/id/195471476/",
    "image_url": "https://cdn1.ozone.ru/s3/multimedia-e/wc250/6023064926.jpg",
    "name": "15.6\" Ноутбук Huawei MateBook 15 Boh-WAP9R (71541704), серый",
    "price": 56990
  },
  {
    "external_url": "/context/detail/id/162908866/",
    "image_url": "https://cdn1.ozone.ru/s3/multimedia-y/wc250/6006922654.jpg",
    "name": "15.6\" Ноутбук Acer Extensa EX215-51G-564K (NX.EG1ER.00E), черный",
    "price": 54595
  },
  {
    "external_url": "/product/15-6-igrovoy-noutbuk-acer-nitro-5-an515-54-55z4-nh-q5ber-02z-chernyy-201203750/",
    "image_url": "https://cdn1.ozone.ru/s3/multimedia-4/wc250/6024998512.jpg",
    "name": "15.6\" Игровой ноутбук Acer Nitro 5 AN515-54-55Z4 (NH.Q5BER.02Z), черный",
    "price": 79990
  },
  {
    "external_url": "/context/detail/id/195471465/",
    "image_url": "https://cdn1.ozone.ru/s3/multimedia-a/wc250/6023064922.jpg",
    "name": "17.3\" Игровой ноутбук ASUS TUF Gaming FX705DT-AU042T (71558186), черный",
    "price": 71990
  },
  {
    "external_url": "/context/detail/id/162304260/",
    "image_url": "https://cdn1.ozone.ru/s3/multimedia-y/wc250/6027153754.jpg",
    "name": "15.6\" Ноутбук Acer Aspire 3 A315-42-R8GL (NX.HF9ER.02H), черный",
    "price": 50260
  },
  {
    "external_url": "/context/detail/id/200093759/",
    "image_url": "https://cdn1.ozone.ru/s3/multimedia-o/wc250/6022553484.jpg",
    "name": "15.6\" Ноутбук Lenovo IdeaPad S145-15API (81UT007FRK), черный",
    "price": 41999
  },
  {
    "external_url": "/product/noutbuk-lenovo-l3-15iml05-81y3001qrk-seryy-175414768/",
    "image_url": "https://cdn1.ozone.ru/s3/multimedia-v/wc250/6015294127.jpg",
    "name": "15.6\" Ноутбук Lenovo L3 15IML05 (81Y3001QRK), серый",
    "price": 42858
  },
  {
    "external_url": "/product/13-3-noutbuk-haier-a914-td0030550ru-chernyy-198548385/",
    "image_url": "https://cdn1.ozone.ru/s3/multimedia-x/wc250/6019822713.jpg",
    "name": "13.3\" Ноутбук Haier A914 (TD0030550RU), черный",
    "price": 29100
  },
  {
    "external_url": "/product/14-noutbuk-huawei-nbl-wap9r-chernyy-180168297/",
    "image_url": "https://cdn1.ozone.ru/s3/multimedia-3/wc250/6027153795.jpg",
    "name": "14\" Ноутбук Huawei Matebook D 14 R7 512GB (53010XJD), серый",
    "price": 54990
  },
  {
    "external_url": "/context/detail/id/201154505/",
    "image_url": "https://cdn1.ozone.ru/s3/multimedia-2/wc250/6027093170.jpg",
    "name": "15.6\" Игровой ноутбук Machenike F117 V (F117-VD-32G-512G-2T), серый",
    "price": 111648
  },
  {
    "external_url": "/context/detail/id/196523646/",
    "image_url": "https://cdn1.ozone.ru/s3/multimedia-x/wc250/6023188785.jpg",
    "name": "16.1\" Ноутбук Xiaomi RedmiBook 16 Ryzen Edition (XMA2002-AN-DOS), серый металлик",
    "price": 68585
  },
  {
    "external_url": "/product/14-noutbuk-hp-14s-fq0027ur-22r21ea-belyy-199868707/",
    "image_url": "https://cdn1.ozone.ru/s3/multimedia-q/wc250/6027153998.jpg",
    "name": "14\" Ноутбук HP 14s-fq0027ur (22R21EA), белый",
    "price": 39220
  },
  {
    "external_url": "/context/detail/id/152341237/",
    "image_url": "https://cdn1.ozone.ru/multimedia/wc250/1022436926.jpg",
    "name": "13.3\" Ноутбук ASUS ASUS ZenBook 13 UX331UN (UX331UN-EG053T) (UX331UN-EG053T), темно-серый Intel i7-8550U / RAM 16GB / SSD 1TB / noODD / 13,3\" Full HD LED / GF MX150(2048) / WiFi / BT / WebCam / Win10H / 1,12кг. Уцененный товар",
    "price": 79990
  },
  {
    "external_url": "/product/noutbuk-acer-aspire-3-a315-42g-r9dx-nx-hf8er-03j-chernyy-175413749/",
    "image_url": "https://cdn1.ozone.ru/s3/multimedia-y/wc250/6027153754.jpg",
    "name": "15.6\" Ноутбук Acer Aspire 3 A315-42G-R9DX (NX.HF8ER.03J), черный",
    "price": 52490
  },
  {
    "external_url": "/context/detail/id/200568477/",
    "image_url": "https://cdn1.ozone.ru/s3/multimedia-r/wc250/6025061751.jpg",
    "name": "15.6\" Игровой ноутбук Acer AN515-43-R7A3 NH.Q6ZER.00Q, черный",
    "price": 64990
  },
  {
    "external_url": "/context/detail/id/167292081/",
    "image_url": "https://cdn1.ozone.ru/s3/multimedia-w/wc250/6009152312.jpg",
    "name": "15.6\" Ноутбук Acer Extensa 15 EX215-51-569V (NX.EFZER.00Q), черный",
    "price": 50940
  },
  {
    "external_url": "/context/detail/id/160716330/",
    "image_url": "https://cdn1.ozone.ru/s3/multimedia-w/wc250/6027153752.jpg",
    "name": "15.6\" Ноутбук Acer Aspire A315-42G-R98F (NX.HF8ER.011), черный",
    "price": 42990
  },
  {
    "external_url": "/context/detail/id/193991558/",
    "image_url": "https://cdn1.ozone.ru/s3/multimedia-w/wc250/6027153932.jpg",
    "name": "15.6\" Ноутбук Acer Aspire A315-42-R11C (NX.HF9ER.045), черный",
    "price": 45940
  },
  {
    "external_url": "/context/detail/id/200735849/",
    "image_url": "https://cdn1.ozone.ru/s3/multimedia-q/wc250/6025166834.jpg",
    "name": "14\" Ноутбук HP 14s-fq0019ur (22P65EA), черный",
    "price": 34575
  },
  {
    "external_url": "/product/13-noutbuk-apple-macbook-pro-13-i5-2-0-16gb-512ssd-sg-serebristyy-179329100/",
    "image_url": "https://cdn1.ozone.ru/s3/multimedia-c/wc250/6017707836.jpg",
    "name": "13\" Ноутбук Apple MacBook Pro 13 i5 2,0/16Gb/512SSD SG, серебристый",
    "price": 173990
  },
  {
    "external_url": "/context/detail/id/162304257/",
    "image_url": "https://cdn1.ozone.ru/s3/multimedia-v/wc250/6016678399.jpg",
    "name": "15.6\" Ноутбук Acer Extensa EX215-51G-349T (NX.EG1ER.002), черный",
    "price": 44972
  },
  {
    "external_url": "/product/15-6-igrovoy-noutbuk-xiaomi-mi-gaming-laptop-chernyy-184906587/",
    "image_url": "https://cdn1.ozone.ru/s3/multimedia-0/wc250/6020056608.jpg",
    "name": "15.6\" Игровой ноутбук Xiaomi Mi Gaming Laptop, черный",
    "price": 131989
  },
  {
    "external_url": "/context/detail/id/195010014/",
    "image_url": "https://cdn1.ozone.ru/s3/multimedia-t/wc250/6022999889.jpg",
    "name": "17.3\" Ноутбук HP 17-by2017ur (24C75EA), черный",
    "price": 42218
  },
  {
    "external_url": "/product/17-3-igrovoy-noutbuk-acer-nitro-5-an517-52-73z0-nh-q80er-008-chernyy-182526751/",
    "image_url": "https://cdn1.ozone.ru/s3/multimedia-1/wc250/6019219141.jpg",
    "name": "17.3\" Игровой ноутбук Acer Nitro 5 AN517-52-73Z0 (NH.Q80ER.008), черный",
    "price": 84990
  },
  {
    "external_url": "/product/noutbuk-hp-17-ca2001ur-s-104l6ea-chernyy-182438978/",
    "image_url": "https://cdn1.ozone.ru/s3/multimedia-x/wc250/6027153861.jpg",
    "name": "17.3\" Ноутбук HP 17-ca2001ur/s (104L6EA), черный",
    "price": 40650
  },
  {
    "external_url": "/product/14-noutbuk-asus-f413fa-eb602t-f413fa-eb602t-chernyy-192792549/",
    "image_url": "https://cdn1.ozone.ru/s3/multimedia-o/wc250/6022290540.jpg",
    "name": "14\" Ноутбук ASUS F413FA-EB602T (F413FA-EB602T), черный",
    "price": 65990
  },
  {
    "external_url": "/product/14-noutbuk-acer-swift-3-sf314-41-r566-nx-heyer-003-serebristyy-184132118/",
    "image_url": "https://cdn1.ozone.ru/s3/multimedia-d/wc250/6027744817.jpg",
    "name": "14\" Ноутбук Acer Swift 3 SF314-41-R566 (NX.HEYER.003), серебристый",
    "price": 36890
  },
  {
    "external_url": "/product/15-6-noutbuk-acer-aspire-5-a515-55-74zx-nx-hsmer-003-serebristyy-184123229/",
    "image_url": "https://cdn1.ozone.ru/s3/multimedia-7/wc250/6019692835.jpg",
    "name": "15.6\" Ноутбук Acer Aspire 5 A515-55-74ZX (NX.HSMER.003), серебристый",
    "price": 64990
  },
  {
    "external_url": "/context/detail/id/201036295/",
    "image_url": "https://cdn1.ozone.ru/s3/multimedia-0/wc250/6025365564.jpg",
    "name": "17.3\" Игровой ноутбук Acer Nitro 5 AN517-52-75S0 NH.Q80ER.004, черный",
    "price": 99990
  },
  {
    "external_url": "/context/detail/id/202160035/",
    "image_url": "https://cdn1.ozone.ru/s3/multimedia-5/wc250/6026125133.jpg",
    "name": "15.6\" Игровой ноутбук Lenovo Gaming 3-15 15ARH05 (82EY000HRU ), черный",
    "price": 74900
  },
  {
    "external_url": "/context/detail/id/201066934/",
    "image_url": "https://cdn1.ozone.ru/s3/multimedia-0/wc250/6016667532.jpg",
    "name": "15.6\" Ноутбук Acer Aspire A315-42-R7KG (NX.HF9ER.034), черный",
    "price": 60599
  },
  {
    "external_url": "/product/13-3-noutbuk-asus-zenbook-edition-30-ux334fl-a4005t-90nb0mw3-m03820-siniy-176890827/",
    "image_url": "https://cdn1.ozone.ru/s3/multimedia-y/wc250/6015870742.jpg",
    "name": "13.3\" Ноутбук ASUS ZenBook Edition 30 UX334FL-A4005T (90NB0MW3-M03820), синий",
    "price": 88100
  },
  {
    "external_url": "/context/detail/id/201044049/",
    "image_url": "https://cdn1.ozone.ru/s3/multimedia-6/wc250/6025383102.jpg",
    "name": "15.6\" Ноутбук HP 15-da3021ur (249Y3EA), черный",
    "price": 52570
  },
  {
    "external_url": "/context/detail/id/196277342/",
    "image_url": "https://cdn1.ozone.ru/s3/multimedia-o/wc250/6023117964.jpg",
    "name": "14\" Ноутбук ASUS K413FA VivoBook 14 Gold (EB526T) (K413FA-EB526T), золотой",
    "price": 43199
  },
  {
    "external_url": "/context/detail/id/199384380/",
    "image_url": "https://cdn1.ozone.ru/s3/multimedia-t/wc250/6024351329.jpg",
    "name": "15.6\" Ноутбук Dell Vostro 3591-6333 (3591-6333), черный, серый",
    "price": 46060
  },
  {
    "external_url": "/context/detail/id/193455840/",
    "image_url": "https://cdn1.ozone.ru/s3/multimedia-z/wc250/6016034615.jpg",
    "name": "15.6\" Ноутбук Lenovo IdeaPad 3 15IIL05 (81WE00KFRK) (81WE00KFRK), синий",
    "price": 55316
  },
  {
    "external_url": "/product/15-6-noutbuk-lenovo-ideapad-5-15iil05-81yk001gru-biryuzovyy-176465119/",
    "image_url": "https://cdn1.ozone.ru/s3/multimedia-z/wc250/6015267023.jpg",
    "name": "15.6\" Ноутбук Lenovo IdeaPad IP5 15IIL05 (81YK001GRU), бирюзовый",
    "price": 73490
  },
  {
    "external_url": "/context/detail/id/195754798/",
    "image_url": "https://cdn1.ozone.ru/s3/multimedia-r/wc250/6022302747.jpg",
    "name": "15.6\" Ноутбук Lenovo V15 (82C50048RU) (82C50048RU), серый",
    "price": 49499
  },
  {
    "external_url": "/context/detail/id/201067408/",
    "image_url": "https://cdn1.ozone.ru/s3/multimedia-u/wc250/6027153750.jpg",
    "name": "15.6\" Ноутбук Acer Aspire 3 A315-42G-R9XV (NX.HF8ER.02D), черный",
    "price": 52899
  },
  {
    "external_url": "/context/detail/id/194637335/",
    "image_url": "https://cdn1.ozone.ru/s3/multimedia-y/wc250/6022872958.jpg",
    "name": "15.6\" Игровой ноутбук Lenovo Creator 5 15IMH05 (82D4004NRU), зеленый",
    "price": 114990
  },
  {
    "external_url": "/context/detail/id/202469073/",
    "image_url": "https://cdn1.ozone.ru/s3/multimedia-o/wc250/6026669688.jpg",
    "name": "15.6\" Ноутбук Acer Extensa 15 EX215-52-54CZ (NX.EG8ER.00Y), черный",
    "price": 41657
  },
  {
    "external_url": "/product/15-6-noutbuk-hp-250-g7-14z75ea-14z75ea-temno-seryy-201815384/",
    "image_url": "https://cdn1.ozone.ru/s3/multimedia-p/wc250/6025905229.jpg",
    "name": "15.6\" Ноутбук HP 250 G7 14Z75EA (14Z75EA), темно-серый",
    "price": 50000
  },
  {
    "external_url": "/product/15-6-igrovoy-noutbuk-acer-predator-triton-500-pt515-52-72kv-nh-q6wer-003-chernyy-182129243/",
    "image_url": "https://cdn1.ozone.ru/s3/multimedia-x/wc250/6019163985.jpg",
    "name": "15.6\" Игровой ноутбук Acer Predator Triton 500 PT515-52-72KV (NH.Q6WER.003), черный",
    "price": 249990
  },
  {
    "external_url": "/product/noutbuk-13-3-lenovo-j700-v-internet-magazine-ozon-tseny-otzyvy-harakteristiki-foto-174100848/",
    "image_url": "https://cdn1.ozone.ru/s3/multimedia-w/wc250/6013408376.jpg",
    "name": "13.3\" Ноутбук Lenovo Ideapad S530-13IWL (81J700BMRU), синий",
    "price": 68730
  },
  {
    "external_url": "/context/detail/id/194037244/",
    "image_url": "https://cdn1.ozone.ru/s3/multimedia-p/wc250/6021018877.jpg",
    "name": "15.6\" Ноутбук Lenovo IdeaPad 5i 15IIL05 (81YK00PGRK), серый",
    "price": 76390
  },
  {
    "external_url": "/product/15-6-noutbuk-lenovo-thinkbook-15-iml-20rw0049ru-seryy-182539281/",
    "image_url": "https://cdn1.ozone.ru/s3/multimedia-9/wc250/6019824021.jpg",
    "name": "15.6\" Ноутбук Lenovo ThinkBook 15-IML (20RW0049RU), серый",
    "price": 54270
  },
  {
    "external_url": "/product/14-noutbuk-acer-aspire-5-a514-53-32qf-nx-huner-004-chernyy-182526727/",
    "image_url": "https://cdn1.ozone.ru/s3/multimedia-6/wc250/6027744846.jpg",
    "name": "14\" Ноутбук Acer Aspire 5 A514-53-32QF (NX.HUNER.004), черный",
    "price": 39990
  },
  {
    "external_url": "/context/detail/id/193546483/",
    "image_url": "https://cdn1.ozone.ru/s3/multimedia-t/wc250/6022297853.jpg",
    "name": "15.6\" Ноутбук HP 255 G7 (2D232EA), черный",
    "price": 49989
  },
  {
    "external_url": "/product/noutbuk-14-xiaomi-mi-redmibook-v-internet-magazine-ozon-tseny-otzyvy-harakteristiki-foto-172011802/",
    "image_url": "https://cdn1.ozone.ru/s3/multimedia-b/wc250/6013238363.jpg",
    "name": "14\" Ноутбук Xiaomi Mi RedmiBook (XMA1901-DA), серебристый",
    "price": 74170
  },
  {
    "external_url": "/context/detail/id/201065566/",
    "image_url": "https://cdn1.ozone.ru/s3/multimedia-g/wc250/6021265000.jpg",
    "name": "15.6\" Ноутбук Intel Dell Vostro 3590 (3590-7551 ) (3590-7551), черный",
    "price": 42399
  },
  {
    "external_url": "/product/15-6-noutbuk-acer-a315-57g-54ba-nx-hzrer-00d-30051498-chernyy-203070936/",
    "image_url": "https://cdn1.ozone.ru/s3/multimedia-l/wc250/6027055749.jpg",
    "name": "15.6\" Ноутбук Acer A315-57G-54BA NX.HZRER.00D (30051498), черный",
    "price": 49990
  },
  {
    "external_url": "/product/14-noutbuk-acer-aspire-5-a514-53-534f-nx-huper-001-serebristyy-182526726/",
    "image_url": "https://cdn1.ozone.ru/s3/multimedia-f/wc250/6019238955.jpg",
    "name": "14\" Ноутбук Acer Aspire 5 A514-53-534F (NX.HUPER.001), серебристый",
    "price": 54990
  },
  {
    "external_url": "/context/detail/id/201044064/",
    "image_url": "https://cdn1.ozone.ru/s3/multimedia-h/wc250/6025383293.jpg",
    "name": "15.6\" Ноутбук Acer Aspire A315-57G-39XC (NX.HZRER.009), черный",
    "price": 55932
  },
  {
    "external_url": "/product/noutbuk-15-6-dell-inspiron-3593-v-internet-magazine-ozon-tseny-otzyvy-harakteristiki-foto-172045420/",
    "image_url": "https://cdn1.ozone.ru/s3/multimedia-0/wc250/6016529832.jpg",
    "name": "15.6\" Ноутбук Dell Inspiron 3593 (3593-8611), серебристый",
    "price": 44066
  },
  {
    "external_url": "/product/15-6-noutbuk-acer-aspire-7-a715-41g-r695-nh-q8qer-00g-chernyy-189953813/",
    "image_url": "https://cdn1.ozone.ru/s3/multimedia-2/wc250/6021456866.jpg",
    "name": "15.6\" Ноутбук Acer Aspire 7 A715-41G-R695 (NH.Q8QER.00G), черный",
    "price": 75990
  },
  {
    "external_url": "/product/15-6-igrovoy-noutbuk-msi-ge66-10sgs-254ru-9s7-154114-254-chernyy-191286025/",
    "image_url": "https://cdn1.ozone.ru/s3/multimedia-r/wc250/6019824147.jpg",
    "name": "15.6\" Игровой ноутбук MSI GE66 10SGS-254RU (9S7-154114-254), черный",
    "price": 232090
  },
  {
    "external_url": "/context/detail/id/202469091/",
    "image_url": "https://cdn1.ozone.ru/s3/multimedia-7/wc250/6026669671.jpg",
    "name": "15.6\" Ноутбук Acer Extensa 15 EX215-22-R842 (NX.EG9ER.00C), черный",
    "price": 41191
  },
  {
    "external_url": "/product/14-noutbuk-acer-swift-3-sf314-41-r8gd-nx-hfeer-00a-siniy-184123226/",
    "image_url": "https://cdn1.ozone.ru/s3/multimedia-e/wc250/6027744854.jpg",
    "name": "14\" Ноутбук Acer Swift 3 SF314-41-R8GD (NX.HFEER.00A), синий",
    "price": 37990
  },
  {
    "external_url": "/product/14-noutbuk-lenovo-81x1004cru-seryy-180551014/",
    "image_url": "https://cdn1.ozone.ru/s3/multimedia-6/wc250/6018342222.jpg",
    "name": "14\" Ноутбук Lenovo Flex 5 14IIL05 (81X1004CRU), серый",
    "price": 71990
  },
  {
    "external_url": "/product/15-6-noutbuk-hp-pavilion-gaming-15-dk1000ur-103r2ea-chernyy-180268183/",
    "image_url": "https://cdn1.ozone.ru/s3/multimedia-1/wc250/6017711965.jpg",
    "name": "15.6\" Игровой ноутбук HP Pavilion Gaming 15-dk1000ur (103R2EA), черный",
    "price": 77100
  },
  {
    "external_url": "/product/15-6-igrovoy-noutbuk-lenovo-legion-5-15imh05h-81y6008kru-81y6008kru-chernyy-181018237/",
    "image_url": "https://cdn1.ozone.ru/s3/multimedia-j/wc250/6016299127.jpg",
    "name": "15.6\" Игровой ноутбук Lenovo Legion 5 15IMH05H (81Y6008KRU) (81Y6008KRU), черный",
    "price": 140890
  },
  {
    "external_url": "/product/14-noutbuk-acer-swift-3-sf314-42-nx-hseer-00j-nx-hseer-00j-serebristyy-180441303/",
    "image_url": "https://cdn1.ozone.ru/s3/multimedia-s/wc250/6014979736.jpg",
    "name": "14\" Ноутбук Acer Swift 3 SF314-42 NX.HSEER.00J (NX.HSEER.00J), серебристый",
    "price": 59913
  },
  {
    "external_url": "/context/detail/id/203070886/",
    "image_url": "https://cdn1.ozone.ru/s3/multimedia-u/wc250/6027055758.jpg",
    "name": "15.6\" Игровой ноутбук Lenovo 81Y40096RK (30053766), черный",
    "price": 76519
  },
  {
    "external_url": "/product/igrovoy-noutbuk-15-6-lenovo-legion-y540-15irh-v-internet-magazine-ozon-tseny-otzyvy-173441627/",
    "image_url": "https://cdn1.ozone.ru/s3/multimedia-r/wc250/6010313271.jpg",
    "name": "15.6\" Игровой ноутбук Lenovo Legion Y540-15IRH (81SX011MRK) (81SX011MRK), черный",
    "price": 107290
  },
  {
    "external_url": "/context/detail/id/201194046/",
    "image_url": "https://cdn1.ozone.ru/s3/multimedia-5/wc250/6016678409.jpg",
    "name": "15.6\" Ноутбук Acer Extensa EX215-51-51CD (NX.EFZER.00P), черный",
    "price": 59100
  },
  {
    "external_url": "/context/detail/id/201815385/",
    "image_url": "https://cdn1.ozone.ru/s3/multimedia-m/wc250/6025904938.jpg",
    "name": "15.6\" Ноутбук HP 250 G7 213R8ES (213R8ES), темно-серый",
    "price": 54396
  },
  {
    "external_url": "/context/detail/id/194037817/",
    "image_url": "https://cdn1.ozone.ru/s3/multimedia-p/wc250/6022685389.jpg",
    "name": "15.6\" Ноутбук Lenovo IdeaPad 5i 15IIL05 (81YK00PERU), синий",
    "price": 80490
  },
  {
    "external_url": "/context/detail/id/194808589/",
    "image_url": "https://cdn1.ozone.ru/s3/multimedia-5/wc250/6022972505.jpg",
    "name": "13.3\" Ноутбук Lenovo ThinkBook Plus (20TG006ERU) (20TG006ERU), серый",
    "price": 118361
  },
  {
    "external_url": "/product/noutbuk-15-6-lenovo-thinkpad-p1-2nd-gen-20qt002lrt-v-internet-magazine-ozon-tseny-otzyvy-174609063/",
    "image_url": "https://cdn1.ozone.ru/s3/multimedia-0/wc250/6010459404.jpg",
    "name": "15.6\" Ноутбук Lenovo ThinkPad P1 (Gen 2) (20QT002LRT), черный",
    "price": 251790
  },
  {
    "external_url": "/product/15-6-noutbuk-lenovo-legion-7i-15imhg05-81yu0010rk-81yu0010rk-seryy-184535003/",
    "image_url": "https://cdn1.ozone.ru/s3/multimedia-p/wc250/6016362745.jpg",
    "name": "15.6\" Ноутбук Lenovo Legion 7i 15IMHg05 (81YU0010RK) (81YU0010RK), серый",
    "price": 177490
  },
  {
    "external_url": "/context/detail/id/201067143/",
    "image_url": "https://cdn1.ozone.ru/s3/multimedia-c/wc250/6017861700.jpg",
    "name": "14\" Ноутбук Lenovo 20RA001DRT, черный",
    "price": 88799
  },
  {
    "external_url": "/product/14-noutbuk-asus-vivobook-14-k413fq-eb033t-90nb0r6f-m00390-chernyy-185029671/",
    "image_url": "https://cdn1.ozone.ru/s3/multimedia-0/wc250/6020109636.jpg",
    "name": "14\" Ноутбук ASUS VivoBook 14 K413FQ-EB033T (90NB0R6F-M00390), черный",
    "price": 68700
  },
  {
    "external_url": "/context/detail/id/192792190/",
    "image_url": "https://cdn1.ozone.ru/s3/multimedia-1/wc250/6022290265.jpg",
    "name": "13.3\" Ноутбук HP 430 G7 (8VT36EA), серый",
    "price": 59990
  },
  {
    "external_url": "/product/15-6-igrovoy-noutbuk-lenovo-ideapad-gaming-3-15arh05-82ey0012ru-82ey0012ru-siniy-181018199/",
    "image_url": "https://cdn1.ozone.ru/s3/multimedia-q/wc250/6015833726.jpg",
    "name": "15.6\" Игровой ноутбук Lenovo IdeaPad Gaming 3 15ARH05 (82EY0012RU) (82EY0012RU), синий",
    "price": 93590
  },
  {
    "external_url": "/context/detail/id/202501481/",
    "image_url": "https://cdn1.ozone.ru/s3/multimedia-u/wc250/6026534010.jpg",
    "name": "13.3\" Ноутбук ASUS VivoBook S S333JQ-EG008T (90NB0QS4-M00240), черный",
    "price": 75275
  },
  {
    "external_url": "/product/14-noutbuk-lenovo-yoga-slim-7-15iil0557-82aa002aru-seryy-184485939/",
    "image_url": "https://cdn1.ozone.ru/s3/multimedia-s/wc250/6019895536.jpg",
    "name": "14\" Ноутбук Lenovo Yoga Slim 7 15IIL0557 (82AA002ARU), серый",
    "price": 87490
  },
  {
    "external_url": "/product/14-noutbuk-acer-travelmate-p2-tmp214-52-53v2-nx-vlher-00l-chernyy-183974297/",
    "image_url": "https://cdn1.ozone.ru/s3/multimedia-4/wc250/6019024348.jpg",
    "name": "14\" Ноутбук Acer TravelMate P2 TMP214-52-53V2 (NX.VLHER.00L), черный",
    "price": 86890
  },
  {
    "external_url": "/context/detail/id/201066118/",
    "image_url": "https://cdn1.ozone.ru/s3/multimedia-5/wc250/6022972505.jpg",
    "name": "13.3\" Ноутбук Lenovo ThinkBook Plus (20TG006ERU) (20TG006ERU), серый",
    "price": 115099
  },
  {
    "external_url": "/context/detail/id/201066625/",
    "image_url": "https://cdn1.ozone.ru/s3/multimedia-b/wc250/6021173807.jpg",
    "name": "13.3\" Ноутбук HP Elite Dragonfly (9VZ94EA), синий",
    "price": 138299
  },
  {
    "external_url": "/product/15-6-noutbuk-dell-xps-15-9500-97-9500-6017-serebristyy-189300456/",
    "image_url": "https://cdn1.ozone.ru/s3/multimedia-a/wc250/6021173050.jpg",
    "name": "15.6\" Ноутбук Dell XPS 15 9500 (9500-6017), серебристый",
    "price": 168690
  },
  {
    "external_url": "/product/15-6-noutbuk-dell-xps-15-7590-59-7590-8765-serebristyy-189300457/",
    "image_url": "https://cdn1.ozone.ru/s3/multimedia-c/wc250/6020600328.jpg",
    "name": "15.6\" Ноутбук Dell XPS 15 7590 (7590-8765), серебристый",
    "price": 165290
  },
  {
    "external_url": "/context/detail/id/201066383/",
    "image_url": "https://cdn1.ozone.ru/s3/multimedia-1/wc250/6019110925.jpg",
    "name": "15.6\" Ноутбук Acer TravelMate P2 TMP215-52-78H9 (NX.VLLER.00K), черный",
    "price": 95599
  },
  {
    "external_url": "/context/detail/id/194416789/",
    "image_url": "https://cdn1.ozone.ru/s3/multimedia-z/wc250/6020603231.jpg",
    "name": "14\" Ноутбук HP EliteBook 840 G6 (6XE53EA), серебристый",
    "price": 122390
  },
  {
    "external_url": "/context/detail/id/203222851/",
    "image_url": "https://cdn1.ozone.ru/s3/multimedia-z/wc250/6022290443.jpg",
    "name": "15.6\" Ноутбук Dell G515-5959 (G515-5959), черный",
    "price": 112790
  },
  {
    "external_url": "/context/detail/id/201066634/",
    "image_url": "https://cdn1.ozone.ru/s3/multimedia-e/wc250/6006096902.jpg",
    "name": "13.3\" Ноутбук HP Elite Dragonfly (8MK78EA), синий",
    "price": 139999
  },
  {
    "external_url": "/context/detail/id/201067105/",
    "image_url": "https://cdn1.ozone.ru/s3/multimedia-1/wc250/6019110925.jpg",
    "name": "15.6\" Ноутбук Acer TravelMate P2 TMP215-52-57ZG (NX.VLLER.00N), черный",
    "price": 79315
  },
  {
    "external_url": "/product/14-noutbuk-lenovo-thinkpad-x1-carbon-gen-8-20u90002rt-20u90002rt-chernyy-181295788/",
    "image_url": "https://cdn1.ozone.ru/s3/multimedia-p/wc250/6016527697.jpg",
    "name": "14\" Ноутбук Lenovo ThinkPad X1 Carbon Gen 8 (20U90002RT) (20U90002RT), черный",
    "price": 157790
  },
  {
    "external_url": "/product/13-3-noutbuk-hp-elitebook-x360-830-7kp93ea-serebristyy-192401421/",
    "image_url": "https://cdn1.ozone.ru/s3/multimedia-c/wc250/6021113472.jpg",
    "name": "13.3\" Ноутбук HP EliteBook x360 830 (7KP93EA), серебристый",
    "price": 143590
  },
  {
    "external_url": "/context/detail/id/201066624/",
    "image_url": "https://cdn1.ozone.ru/s3/multimedia-w/wc250/6018249260.jpg",
    "name": "13.3\" Ноутбук Lenovo ThinkPad X13 Yoga Gen 1 (20SX001GRT) (20SX001GRT), черный",
    "price": 145099
  },
  {
    "external_url": "/context/detail/id/199678540/",
    "image_url": "https://cdn1.ozone.ru/s3/multimedia-a/wc250/6024560398.jpg",
    "name": "13.3\" Ноутбук HP EliteBook 830 G7 (1J5T9EA), серебристый",
    "price": 119890
  },
  {
    "external_url": "/product/14-noutbuk-lenovo-thinkpad-x1-yoga-gen-5-2-20ub0004rt-chernyy-183153882/",
    "image_url": "https://cdn1.ozone.ru/s3/multimedia-v/wc250/6019461091.jpg",
    "name": "14\" Ноутбук Lenovo ThinkPad X1 Yoga (Gen 5)2 (20UB0004RT), черный",
    "price": 191590
  },
  {
    "external_url": "/product/14-noutbuk-lenovo-thinkpad-l4905-20q50020rt-chernyy-182527732/",
    "image_url": "https://cdn1.ozone.ru/s3/multimedia-1/wc250/6010380385.jpg",
    "name": "14\" Ноутбук Lenovo ThinkPad L4905 (20Q50020RT), черный",
    "price": 112690
  },
  {
    "external_url": "/context/detail/id/204194163/",
    "image_url": "https://cdn1.ozone.ru/s3/multimedia-1/wc250/6019110925.jpg",
    "name": "15.6\" Ноутбук Acer TravelMate P2 TMP215-52-32X3 (NX.VLLER.00Q), черный",
    "price": 61647
  },
  {
    "external_url": "/context/detail/id/195156786/",
    "image_url": "https://cdn1.ozone.ru/s3/multimedia-4/wc250/6025581856.jpg",
    "name": "14\" Ноутбук ASUS Ноутбук ASUS, UX430UA (90NB0EC5-M09430), голубой. Уцененный товар",
    "price": 58700
  },
  {
    "external_url": "/context/detail/id/199452580/",
    "image_url": "https://cdn1.ozone.ru/multimedia/wc250/1026505487.jpg",
    "name": "13.3\" Ноутбук ASUS VivoBook S13 S330UN-EY024T (90NB0JD2-M00620), золотой. Уцененный товар",
    "price": 43608
  },
  {
    "external_url": "/context/detail/id/202329459/",
    "image_url": "https://cdn1.ozone.ru/multimedia/wc250/1023986183.jpg",
    "name": "15.6\" Игровой ноутбук Dell Ноутбук Dell G515-7305 (G515-7305), красный. Уцененный товар",
    "price": 53200
  },
  {
    "external_url": "/context/detail/id/195156798/",
    "image_url": "https://cdn1.ozone.ru/s3/multimedia-o/wc250/6028011588.jpg",
    "name": "15.6\" Игровой ноутбук Lenovo IdeaPad L340 Gaming (81LK009YRU), черный. Уцененный товар",
    "price": 58990
  },
  {
    "external_url": "/context/detail/id/194083405/",
    "image_url": "https://cdn1.ozone.ru/s3/multimedia-d/wc250/6000033529.jpg",
    "name": "14\" Ноутбук HP Pavilion 14-ce2013ur (6RV35EA), золотой",
    "price": 92934
  },
  {
    "external_url": "/context/detail/id/193949558/",
    "image_url": "https://cdn1.ozone.ru/s3/multimedia-v/wc250/6022679311.jpg",
    "name": "14\" Ноутбук HP EliteBook x360 1040 G5 (5SR10EA), серебристый",
    "price": 130652
  },
  {
    "external_url": "/context/detail/id/194417072/",
    "image_url": "https://cdn1.ozone.ru/s3/multimedia-y/wc250/6022784398.jpg",
    "name": "13.3\" Ноутбук HP EliteBook x360 1030 G3 (4QY23EA), серебристый, черный",
    "price": 139093
  },
  {
    "external_url": "/product/14-noutbuk-lenovo-t490-i5-8265u-chernyy-178259457/",
    "image_url": "https://cdn1.ozone.ru/s3/multimedia-r/wc250/6017137791.jpg",
    "name": "14\" Ноутбук Lenovo T490 (i5-8265U), черный",
    "price": 79985
  },
  {
    "external_url": "/context/detail/id/198781220/",
    "image_url": "https://cdn1.ozone.ru/s3/multimedia-i/wc250/6022574430.jpg",
    "name": "14\" Ноутбук HP ProBook 440 G7 (2D291EA) (2D291EA), серебристый",
    "price": 63189
  },
  {
    "external_url": "/context/detail/id/193925690/",
    "image_url": "https://cdn1.ozone.ru/s3/multimedia-i/wc250/6022574430.jpg",
    "name": "14\" Ноутбук HP ProBook 440 G7 (8VU04EA) (8VU04EA), серебристый",
    "price": 80439
  },
  {
    "external_url": "/context/detail/id/198759810/",
    "image_url": "https://cdn1.ozone.ru/s3/multimedia-r/wc250/6024127839.jpg",
    "name": "14\" Ноутбук Acer Swift SF714-52T-76X9 (NX.HB4ER.003), белый",
    "price": 144999
  },
  {
    "external_url": "/context/detail/id/199390008/",
    "image_url": "https://cdn1.ozone.ru/s3/multimedia-q/wc250/6024359354.jpg",
    "name": "14\" Ноутбук Lenovo Yoga S940-14 (81Q8002YRU) (81Q8002YRU), серый",
    "price": 174990
  },
  {
    "external_url": "/context/detail/id/199818227/",
    "image_url": "https://cdn1.ozone.ru/s3/multimedia-4/wc250/6019024348.jpg",
    "name": "14\" Ноутбук Acer TravelMate P2 TMP214-52-58ZN (NX.VLHER.00F), черный",
    "price": 65549
  },
  {
    "external_url": "/context/detail/id/199388297/",
    "image_url": "https://cdn1.ozone.ru/s3/multimedia-p/wc250/6024356329.jpg",
    "name": "15.6\" Ноутбук HP EliteBook 850 G6 (6XD79EA) (6XD79EA), серебристый",
    "price": 95519
  },
  {
    "external_url": "/context/detail/id/167292080/",
    "image_url": "https://cdn1.ozone.ru/s3/multimedia-y/wc250/6009152098.jpg",
    "name": "15.6\" Ноутбук Acer Extensa 15 EX215-51-59Y1 (NX.EFZER.00M), черный",
    "price": 45330
  },
  {
    "external_url": "/product/15-6-noutbuk-honor-magicbook-15-256gb-chernyy-182537453/",
    "image_url": "https://cdn1.ozone.ru/s3/multimedia-2/wc250/6019358282.jpg",
    "name": "15.6\" Ноутбук Honor MagicBook 15 256GB, серый",
    "price": 49990
  },
  {
    "external_url": "/context/detail/id/202728231/",
    "image_url": "https://cdn1.ozone.ru/s3/multimedia-1/wc250/6026708653.jpg",
    "name": "15.6\" Ноутбук HP Pavilion Gaming 15-ec0061ur (22R03EA), черный",
    "price": 63300
  },
  {
    "external_url": "/product/15-6-noutbuk-lenovo-thinkbook-15-iil-20sm009mru-20sm009mru-seryy-182226802/",
    "image_url": "https://cdn1.ozone.ru/s3/multimedia-t/wc250/6019822241.jpg",
    "name": "15.6\" Ноутбук Lenovo ThinkBook 15-IIL (20SM009MRU), серебристый",
    "price": 78390
  },
  {
    "external_url": "/context/detail/id/201815394/",
    "image_url": "https://cdn1.ozone.ru/s3/multimedia-z/wc250/6025904915.jpg",
    "name": "15.6\" Игровой ноутбук MSI GL65 10SCSR-049RU (9S7-16U822-049), черный",
    "price": 92462
  },
  {
    "external_url": "/product/noutbuk-14-acer-travelmate-tmp648-g3-m-53c7-v-internet-magazine-ozon-tseny-otzyvy-172764938/",
    "image_url": "https://cdn1.ozone.ru/multimedia/wc250/1028548631.jpg",
    "name": "14\" Ноутбук Acer TravelMate TMP648-G3-M-53C7, черный",
    "price": 79000
  },
  {
    "external_url": "/product/15-6-igrovoy-noutbuk-asus-tuf-a15-fx506iu-hn291-90nr03n1-m05200-seryy-183391259/",
    "image_url": "https://cdn1.ozone.ru/s3/multimedia-q/wc250/6027153890.jpg",
    "name": "15.6\" Игровой ноутбук ASUS TUF A15 FX506IU-HN291 (90NR03N1-M05200), серый",
    "price": 92185
  },
  {
    "external_url": "/product/14-noutbuk-asus-pro-p1440fa-fa2078-90nx0211-m26390-seryy-182535881/",
    "image_url": "https://cdn1.ozone.ru/s3/multimedia-6/wc250/6019384386.jpg",
    "name": "14\" Ноутбук ASUS PRO P1440FA-FA2078 (90NX0211-M26390), серый",
    "price": 41051
  },
  {
    "external_url": "/context/detail/id/197217026/",
    "image_url": "https://cdn1.ozone.ru/s3/multimedia-p/wc250/6023645509.jpg",
    "name": "14\" Ноутбук Lenovo V14-ADA (82C60059RU), серый",
    "price": 33511
  },
  {
    "external_url": "/product/noutbuk-honor-magicbook-15-boh-waq9hnr-53010uav-176631626/",
    "image_url": "https://cdn1.ozone.ru/s3/multimedia-a/wc250/6016064362.jpg",
    "name": "15.6\" Ноутбук Honor MagicBook 15 256GB (53010UAV), серый",
    "price": 49990
  },
  {
    "external_url": "/context/detail/id/201044059/",
    "image_url": "https://cdn1.ozone.ru/s3/multimedia-7/wc250/6025383247.jpg",
    "name": "15.6\" Игровой ноутбук HP Pavilion Gaming 15-ec0061ur (22R03EA), черный",
    "price": 68351
  },
  {
    "external_url": "/context/detail/id/160716569/",
    "image_url": "https://cdn1.ozone.ru/s3/multimedia-o/wc250/6004378992.jpg",
    "name": "14\" Ноутбук HP 14s-dq1013ur (8PJ21EA), серебристый",
    "price": 54060
  },
  {
    "external_url": "/product/17-3-igrovoy-noutbuk-acer-nitro-5-an517-52-78j6-nh-q8ker-009-chernyy-182526753/",
    "image_url": "https://cdn1.ozone.ru/s3/multimedia-1/wc250/6019219141.jpg",
    "name": "17.3\" Игровой ноутбук Acer Nitro 5 AN517-52-78J6 (NH.Q8KER.009), черный",
    "price": 112990
  },
  {
    "external_url": "/context/detail/id/193991571/",
    "image_url": "https://cdn1.ozone.ru/s3/multimedia-c/wc250/6022727820.jpg",
    "name": "15.6\" Ноутбук Acer Extensa EX215-51-59LR (NX.EFZER.014), черный",
    "price": 45570
  },
  {
    "external_url": "/context/detail/id/193813186/",
    "image_url": "https://cdn1.ozone.ru/s3/multimedia-x/wc250/6022302717.jpg",
    "name": "14\" Ноутбук HP ProBook 455 G7 (7RX17AV), серебристый",
    "price": 63381
  },
  {
    "external_url": "/context/detail/id/193991566/",
    "image_url": "https://cdn1.ozone.ru/s3/multimedia-6/wc250/6022727814.jpg",
    "name": "15.6\" Ноутбук Acer Aspire A315-56-31JS (NX.HS5ER.001), черный",
    "price": 44990
  },
  {
    "external_url": "/product/13-3-noutbuk-asus-zenbook-13-ux331fn-em039t-90nb0ke2-m01590-seryy-175410990/",
    "image_url": "https://cdn1.ozone.ru/s3/multimedia-a/wc250/6010824202.jpg",
    "name": "13.3\" Ноутбук ASUS ZenBook 13 UX331FN-EM039T (90NB0KE2-M01590), серый",
    "price": 61400
  },
  {
    "external_url": "/product/noutbuk-lenovo-ip-3-15iil05-81we007hrk-platinovyy-seryy-182449850/",
    "image_url": "https://cdn1.ozone.ru/s3/multimedia-3/wc250/6019730631.jpg",
    "name": "15.6\" Ноутбук Lenovo IdeaPad 3 15IIL05 (81WE007HRK), платиновый серый",
    "price": 52473
  },
  {
    "external_url": "/context/detail/id/193991555/",
    "image_url": "https://cdn1.ozone.ru/s3/multimedia-u/wc250/6027153930.jpg",
    "name": "15.6\" Ноутбук Acer Aspire A315-42-R4MD (NX.HF9ER.049), черный",
    "price": 52880
  },
  {
    "external_url": "/context/detail/id/195471455/",
    "image_url": "https://cdn1.ozone.ru/s3/multimedia-o/wc250/6027153924.jpg",
    "name": "15.6\" Игровой ноутбук Lenovo IdeaPad Gaming 3 15ARH05 (82EY000GRU), черный",
    "price": 79990
  },
  {
    "external_url": "/product/14-noutbuk-asus-vivobook-14-k413fq-eb033t-90nb0r6f-m00390-chernyy-188486320/",
    "image_url": "https://cdn1.ozone.ru/s3/multimedia-t/wc250/6020497313.jpg",
    "name": "14\" Ноутбук ASUS VivoBook 14 K413FQ-EB033T (90NB0R6F-M00390), черный",
    "price": 62570
  },
  {
    "external_url": "/product/15-6-noutbuk-acer-aspire-5-a515-44-r472-nx-hw4er-003-chernyy-184132242/",
    "image_url": "https://cdn1.ozone.ru/s3/multimedia-z/wc250/6019238975.jpg",
    "name": "15.6\" Ноутбук Acer Aspire 5 A515-44-R472 (NX.HW4ER.003), черный",
    "price": 50490
  },
  {
    "external_url": "/context/detail/id/199402701/",
    "image_url": "https://cdn1.ozone.ru/s3/multimedia-h/wc250/6025145009.jpg",
    "name": "15.6\" Ноутбук HP 22R35EA (22R35EA), серебристый",
    "price": 43770
  },
  {
    "external_url": "/product/15-6-noutbuk-lenovo-ideapad-3-81we00kfrk-siniy-182537678/",
    "image_url": "https://cdn1.ozone.ru/s3/multimedia-2/wc250/6019734158.jpg",
    "name": "15.6\" Ноутбук Lenovo IdeaPad 3 (81WE00KFRK), синий",
    "price": 49570
  },
  {
    "external_url": "/product/15-6-igrovoy-noutbuk-lenovo-legion-5pi-15imh05-82ay0020rk-temno-seryy-180728049/",
    "image_url": "https://cdn1.ozone.ru/s3/multimedia-8/wc250/6027746540.jpg",
    "name": "15.6\" Игровой ноутбук Lenovo Legion 5Pi 15IMH05 (82AY0020RK), темно-серый",
    "price": 90990
  },
  {
    "external_url": "/context/detail/id/162304258/",
    "image_url": "https://cdn1.ozone.ru/s3/multimedia-8/wc250/6016678412.jpg",
    "name": "15.6\" Ноутбук Acer Extensa EX215-51G-33EP (NX.EG1ER.00C), черный",
    "price": 42050
  },
  {
    "external_url": "/context/detail/id/199868697/",
    "image_url": "https://cdn1.ozone.ru/s3/multimedia-b/wc250/6026013071.jpg",
    "name": "15.6\" Ноутбук HP 15-db1244ur (22N11EA), серый",
    "price": 36883
  },
  {
    "external_url": "/product/15-6-noutbuk-hp-15s-fq1005ur-8kj95ea-serebristyy-179266483/",
    "image_url": "https://cdn1.ozone.ru/s3/multimedia-q/wc250/6017711414.jpg",
    "name": "15.6\" Ноутбук HP 15s-fq1005ur (8KJ95EA), серебристый",
    "price": 51450
  },
  {
    "external_url": "/product/13-3-noutbuk-asus-zenbook-edition-30-ux334fl-a4003t-90nb0mw3-m03480-belyy-176890838/",
    "image_url": "https://cdn1.ozone.ru/s3/multimedia-1/wc250/6016149241.jpg",
    "name": "13.3\" Ноутбук ASUS ZenBook UX334FL-A4003T (90NB0MW3-M03480), синий",
    "price": 78000
  },
  {
    "external_url": "/product/14-noutbuk-acer-swift-5-sf514-54t-56gp-nx-hlger-003-belyy-181119417/",
    "image_url": "https://cdn1.ozone.ru/s3/multimedia-q/wc250/6018550790.jpg",
    "name": "14\" Ноутбук Acer Swift 5 SF514-54T-56GP (NX.HLGER.003), белый",
    "price": 79990
  },
  {
    "external_url": "/context/detail/id/198065960/",
    "image_url": "https://cdn1.ozone.ru/s3/multimedia-h/wc250/6019254473.jpg",
    "name": "15.6\" Игровой ноутбук Acer Nitro 5 AN515-55-568E (NH.Q7PER.007), черный",
    "price": 88570
  },
  {
    "external_url": "/product/noutbuk-15-6-asus-zenbook-flip-15-ux563fd-ez008t-v-internet-magazine-ozon-tseny-otzyvy-172477718/",
    "image_url": "https://cdn1.ozone.ru/s3/multimedia-i/wc250/6011352618.jpg",
    "name": "15.6\" Ноутбук ASUS ZenBook Flip 15 UX563FD-EZ008T (90NB0NT1-M00810), серый",
    "price": 98065
  },
  {
    "external_url": "/product/13-3-noutbuk-asus-ux334flc-a3108t-90nb0mw1-m04860-siniy-182535867/",
    "image_url": "https://cdn1.ozone.ru/s3/multimedia-h/wc250/6019384145.jpg",
    "name": "13.3\" Ноутбук ASUS UX334FLC-A3108T (90NB0MW1-M04860), синий",
    "price": 77210
  },
  {
    "external_url": "/product/13-3-noutbuk-acer-swift-3-sf313-52-56l2-nx-hqwer-00a-serebristyy-181119341/",
    "image_url": "https://cdn1.ozone.ru/s3/multimedia-n/wc250/6018486131.jpg",
    "name": "13.3\" Ноутбук Acer Swift 3 SF313-52-56L2 (NX.HQWER.00A), серебристый",
    "price": 64990
  },
  {
    "external_url": "/product/15-6-noutbuk-acer-aspire-3-a315-42g-r6ef-nx-hf8er-03a-chernyy-176452922/",
    "image_url": "https://cdn1.ozone.ru/s3/multimedia-s/wc250/6011352376.jpg",
    "name": "15.6\" Ноутбук Acer Aspire 3 A315-42G-R6EF (NX.HF8ER.03A), черный",
    "price": 48013
  },
  {
    "external_url": "/context/detail/id/201815371/",
    "image_url": "https://cdn1.ozone.ru/s3/multimedia-1/wc250/6025904881.jpg",
    "name": "15.6\" Ноутбук Acer Aspire 3 A315-34-P6PE (NX.HE3EU.02V), черный",
    "price": 37766
  },
  {
    "external_url": "/context/detail/id/160716496/",
    "image_url": "https://cdn1.ozone.ru/s3/multimedia-y/wc250/6011094046.jpg",
    "name": "15.6\" Игровой ноутбук Acer Nitro 5 AN515-54-76DE (NH.Q5BER.02D), черный",
    "price": 94080
  },
  {
    "external_url": "/context/detail/id/202728207/",
    "image_url": "https://cdn1.ozone.ru/s3/multimedia-7/wc250/6026708659.jpg",
    "name": "17.3\" Ноутбук HP 17-ca1066ur (22Q71EA) (22Q71EA), серебристый",
    "price": 60900
  },
  {
    "external_url": "/product/15-6-noutbuk-acer-a515-53-nx-h6fer-002-chernyy-201067580/",
    "image_url": "https://cdn1.ozone.ru/s3/multimedia-4/wc250/6019461496.jpg",
    "name": "15.6\" Ноутбук Acer A515-53 (NX.H6FER.002), черный",
    "price": 48400
  },
  {
    "external_url": "/context/detail/id/201286472/",
    "image_url": "https://cdn1.ozone.ru/s3/multimedia-s/wc250/6019110484.jpg",
    "name": "15.6\" Ноутбук HP 15-db1209ur/s (104G5EA), черный",
    "price": 58500
  },
  {
    "external_url": "/context/detail/id/200843717/",
    "image_url": "https://cdn1.ozone.ru/s3/multimedia-n/wc250/6025241099.jpg",
    "name": "14\" Ноутбук HP 14-cf2003ur (22Z36EA), черный",
    "price": 40041
  },
  {
    "external_url": "/context/detail/id/200994449/",
    "image_url": "https://cdn1.ozone.ru/s3/multimedia-m/wc250/6025327102.jpg",
    "name": "14\" Ноутбук ASUS PRO P5440FA-BM0281T (90NX01X1-M04170), серый",
    "price": 83990
  },
  {
    "external_url": "/product/14-noutbuk-acer-aspire-5-a514-53-37yr-nx-huser-001-serebristyy-182526717/",
    "image_url": "https://cdn1.ozone.ru/s3/multimedia-h/wc250/6027744821.jpg",
    "name": "14\" Ноутбук Acer Aspire 5 A514-53-37YR (NX.HUSER.001), серебристый",
    "price": 41990
  },
  {
    "external_url": "/context/detail/id/202238611/",
    "image_url": "https://cdn1.ozone.ru/s3/multimedia-6/wc250/6026202678.jpg",
    "name": "15.6\" Ноутбук Xiaomi Mi Notebook Pro (JYU4200CN), серый",
    "price": 89990
  },
  {
    "external_url": "/context/detail/id/202135342/",
    "image_url": "https://cdn1.ozone.ru/s3/multimedia-w/wc250/6026107160.jpg",
    "name": "14\" Ноутбук ASUS UX463FL-AI043T (90NB0NW1-M00570), серый",
    "price": 81200
  },
  {
    "external_url": "/context/detail/id/195062846/",
    "image_url": "https://cdn1.ozone.ru/s3/multimedia-9/wc250/6027548721.jpg",
    "name": "17\" Ноутбук Dell XPS 17 9700 (9700-6703), серебристый",
    "price": 242390
  },
  {
    "external_url": "/context/detail/id/199681075/",
    "image_url": "https://cdn1.ozone.ru/s3/multimedia-o/wc250/6022281072.jpg",
    "name": "15.6\" Ноутбук HP 15s-fq1090ur (22U89EA), серый",
    "price": 59590
  },
  {
    "external_url": "/context/detail/id/200444232/",
    "image_url": "https://cdn1.ozone.ru/s3/multimedia-g/wc250/6024956512.jpg",
    "name": "14\" Ноутбук Lenovo S540-14IML (81NF006SRK), серый",
    "price": 59490
  },
  {
    "external_url": "/context/detail/id/203312887/",
    "image_url": "https://cdn1.ozone.ru/s3/multimedia-6/wc250/6027238578.jpg",
    "name": "15.6\" Ноутбук HP Pavilion x360 14-dw0000ur (22Z39EA), зеленый",
    "price": 49390
  },
  {
    "external_url": "/context/detail/id/192602049/",
    "image_url": "https://cdn1.ozone.ru/s3/multimedia-p/wc250/6022066621.jpg",
    "name": "14\" Ноутбук ASUS ExpertBook B9450FA-BM0555R (90NX02K1-M06670), синий",
    "price": 155090
  },
  {
    "external_url": "/context/detail/id/204298304/",
    "image_url": "https://cdn1.ozone.ru/s3/multimedia-u/wc250/6027736194.jpg",
    "name": "15.6\" Ноутбук Acer Aspire 5 A515-44G-R0ER (NX.HW5ER.008), черный",
    "price": 61400
  },
  {
    "external_url": "/product/noutbuk-acer-extensa-ex215-51k-515g-nx-efper-011-chernyy-182201443/",
    "image_url": "https://cdn1.ozone.ru/s3/multimedia-v/wc250/6019217659.jpg",
    "name": "15.6\" Ноутбук Acer Extensa EX215-51K-515G (NX.EFPER.011), черный",
    "price": 50000
  },
  {
    "external_url": "/context/detail/id/194808748/",
    "image_url": "https://cdn1.ozone.ru/s3/multimedia-b/wc250/6011353043.jpg",
    "name": "14\" Ноутбук Dell Inspiron 5490 (5490-8412) (5490-8412), серебристый",
    "price": 75990
  },
  {
    "external_url": "/context/detail/id/194810876/",
    "image_url": "https://cdn1.ozone.ru/s3/multimedia-9/wc250/6022424769.jpg",
    "name": "15.6\" Ноутбук Dell G5 5500 (G515-7748), черный",
    "price": 91989
  },
  {
    "external_url": "/product/15-6-igrovoy-noutbuk-lenovo-ideapad-gaming-3-15arh05-82ey0012ru-siniy-190811525/",
    "image_url": "https://cdn1.ozone.ru/s3/multimedia-n/wc250/6027153923.jpg",
    "name": "15.6\" Игровой ноутбук Lenovo IdeaPad Gaming 3 15ARH05 (82EY0012RU), синий",
    "price": 86440
  },
  {
    "external_url": "/product/15-6-noutbuk-lenovo-yoga-s740-15-81nx003tru-81nx003tru-seryy-177212957/",
    "image_url": "https://cdn1.ozone.ru/s3/multimedia-c/wc250/6024357648.jpg",
    "name": "15.6\" Ноутбук Lenovo Yoga S740-15 (81NX003TRU) (81NX003TRU), серый",
    "price": 171690
  },
  {
    "external_url": "/context/detail/id/204853622/",
    "image_url": "https://cdn1.ozone.ru/s3/multimedia-1/wc250/6026708653.jpg",
    "name": "15.6\" Ноутбук HP Pavilion Gaming 15-ec0061ur (22R03EA), черный",
    "price": 72990
  },
  {
    "external_url": "/context/detail/id/201286473/",
    "image_url": "https://cdn1.ozone.ru/s3/multimedia-t/wc250/6022297853.jpg",
    "name": "15.6\" Ноутбук HP 255 G7 (17S95ES), черный",
    "price": 54100
  },
  {
    "external_url": "/product/14-noutbuk-acer-aspire-5-a514-53-52fe-nx-huner-003-chernyy-182526725/",
    "image_url": "https://cdn1.ozone.ru/s3/multimedia-c/wc250/6019238952.jpg",
    "name": "14\" Ноутбук Acer Aspire 5 A514-53-52FE (NX.HUNER.003), черный",
    "price": 54990
  },
  {
    "external_url": "/product/noutbuk-14-lenovo-yoga-s940-14iwl-v-internet-magazine-ozon-tseny-otzyvy-harakteristiki-foto-172721693/",
    "image_url": "https://cdn1.ozone.ru/s3/multimedia-k/wc250/6010621244.jpg",
    "name": "14\" Ноутбук Lenovo Yoga S940-14IWL (81Q7000HRU), темно-серый",
    "price": 148890
  },
  {
    "external_url": "/context/detail/id/192732704/",
    "image_url": "https://cdn1.ozone.ru/s3/multimedia-z/wc250/6020600351.jpg",
    "name": "14\" Ноутбук Dell Inspiron 7490 (7490-7063), черный",
    "price": 112890
  },
  {
    "external_url": "/context/detail/id/194733211/",
    "image_url": "https://cdn1.ozone.ru/s3/multimedia-y/wc250/6022872958.jpg",
    "name": "15.6\" Игровой ноутбук Lenovo Creator 5 15IMH05 (82D4004MRU), зеленый",
    "price": 89990
  },
  {
    "external_url": "/product/17-3-igrovoy-noutbuk-hp-pavilion-gaming-17-cd1063ur-22q98ea-chernyy-203269182/",
    "image_url": "https://cdn1.ozone.ru/s3/multimedia-e/wc250/6027071006.jpg",
    "name": "17.3\" Игровой ноутбук HP Pavilion Gaming 17-cd1063ur (22Q98EA), черный",
    "price": 122900
  },
  {
    "external_url": "/product/15-6-igrovoy-noutbuk-lenovo-legion-5-15imh05h-81y6008hru-81y6008hru-chernyy-181018247/",
    "image_url": "https://cdn1.ozone.ru/s3/multimedia-j/wc250/6016299127.jpg",
    "name": "15.6\" Игровой ноутбук Lenovo Legion 5 15IMH05H (81Y6008HRU) (81Y6008HRU), черный",
    "price": 113590
  },
  {
    "external_url": "/product/15-6-noutbuk-lenovo-thinkpad-x1-extreme-20qv0011rt-chernyy-189030331/",
    "image_url": "https://cdn1.ozone.ru/s3/multimedia-d/wc250/6010482097.jpg",
    "name": "15.6\" Ноутбук Lenovo ThinkPad X1 Extreme (20QV0011RT), черный",
    "price": 280790
  },
  {
    "external_url": "/context/detail/id/204398570/",
    "image_url": "https://cdn1.ozone.ru/s3/multimedia-z/wc250/6019238975.jpg",
    "name": "15.6\" Ноутбук Acer Aspire 5 A515-44-R3N8 (NX.HW3ER.00E), черный",
    "price": 72487
  },
  {
    "external_url": "/context/detail/id/199585038/",
    "image_url": "https://cdn1.ozone.ru/s3/multimedia-1/wc250/6020600389.jpg",
    "name": "17.3\" Ноутбук Dell Precision 5750 (5750-6734), серый",
    "price": 238490
  },
  {
    "external_url": "/product/15-6-noutbuk-lenovo-ideapad-3-15iil05-81we009dru-81we009dru-seryy-metallik-180552293/",
    "image_url": "https://cdn1.ozone.ru/s3/multimedia-1/wc250/6015871933.jpg",
    "name": "15.6\" Ноутбук Lenovo IdeaPad 3 15IIL05 (81WE009DRU) (81WE009DRU), серый металлик",
    "price": 57290
  },
  {
    "external_url": "/product/14-noutbuk-dell-inspiron-7490-7490-7025-serebristyy-190253362/",
    "image_url": "https://cdn1.ozone.ru/s3/multimedia-b/wc250/6004664999.jpg",
    "name": "14\" Ноутбук Dell Inspiron 7490 (7490-7025), серебристый",
    "price": 80040
  },
  {
    "external_url": "/product/14-noutbuk-msi-prestige-14-a10sc-057ru-9s7-14c112-057-seryy-185443067/",
    "image_url": "https://cdn1.ozone.ru/s3/multimedia-7/wc250/6009116863.jpg",
    "name": "14\" Ноутбук MSI Prestige 14 A10SC-057RU (9S7-14C112-057), серый",
    "price": 106290
  },
  {
    "external_url": "/context/detail/id/196277309/",
    "image_url": "https://cdn1.ozone.ru/s3/multimedia-l/wc250/6022745433.jpg",
    "name": "15.6\" Ноутбук Lenovo IdeaPad Gaming 3-15  (82EY000GRU), черный",
    "price": 84329
  },
  {
    "external_url": "/product/15-6-noutbuk-acer-aspire-3-a315-42-r5l9-nx-hf9er-03k-chernyy-190420642/",
    "image_url": "https://cdn1.ozone.ru/s3/multimedia-y/wc250/6027153754.jpg",
    "name": "15.6\" Ноутбук Acer Aspire 3 A315-42-R5L9 (NX.HF9ER.03K), черный",
    "price": 59990
  },
  {
    "external_url": "/context/detail/id/204774266/",
    "image_url": "https://cdn1.ozone.ru/s3/multimedia-4/wc250/6019024348.jpg",
    "name": "14\" Ноутбук Acer TMP214-52-335A (NX.VLHER.00P), черный",
    "price": 59913
  },
  {
    "external_url": "/context/detail/id/204394705/",
    "image_url": "https://cdn1.ozone.ru/s3/multimedia-w/wc250/6027843476.jpg",
    "name": "14\" Ноутбук Dell Vostro 5401 (5401-2741) (5401-2741), серый",
    "price": 63381
  },
  {
    "external_url": "/context/detail/id/203070847/",
    "image_url": "https://cdn1.ozone.ru/s3/multimedia-h/wc250/6027055745.jpg",
    "name": "13.3\" Ноутбук Lenovo 20RR0002RU (30053277), серый",
    "price": 84990
  },
  {
    "external_url": "/product/17-3-noutbuk-dell-precision-7740-7740-5291-seryy-191277565/",
    "image_url": "https://cdn1.ozone.ru/s3/multimedia-h/wc250/6020600369.jpg",
    "name": "17.3\" Ноутбук Dell Precision 7740 (7740-5291), серый",
    "price": 235590
  },
  {
    "external_url": "/context/detail/id/204048068/",
    "image_url": "https://cdn1.ozone.ru/s3/multimedia-w/wc250/6021304112.jpg",
    "name": "15.6\" Ноутбук Acer ConceptD 7 CN715-71-7383 (NX.C4KER.006), белый",
    "price": 279990
  },
  {
    "external_url": "/product/noutbuk-14-lenovo-thinkpad-t490-v-internet-magazine-ozon-tseny-otzyvy-harakteristiki-foto-173054092/",
    "image_url": "https://cdn1.ozone.ru/multimedia/wc250/1036621078.jpg",
    "name": "14\" Ноутбук Lenovo ThinkPad T490 (20N2000BRT), черный",
    "price": 122990
  },
  {
    "external_url": "/context/detail/id/204772897/",
    "image_url": "https://cdn1.ozone.ru/s3/multimedia-m/wc250/6027953662.jpg",
    "name": "15.6\" Ноутбук Acer Aspire A315-57G-39XC (NX.HZRER.009), черный",
    "price": 60945
  },
  {
    "external_url": "/product/noutbuk-14-lenovo-thinkpad-e14-20ra001crt-v-internet-magazine-ozon-tseny-otzyvy-harakteristiki-foto-174609035/",
    "image_url": "https://cdn1.ozone.ru/s3/multimedia-e/wc250/6010332698.jpg",
    "name": "14\" Ноутбук Lenovo ThinkPad E14 20RA001CRT (20RA001CRT), серый",
    "price": 97390
  },
  {
    "external_url": "/product/15-6-noutbuk-dell-g3-3500-g315-5843-belyy-189808549/",
    "image_url": "https://cdn1.ozone.ru/s3/multimedia-u/wc250/6019447842.jpg",
    "name": "15.6\" Ноутбук Dell G3 3500 (G315-5843), белый",
    "price": 102190
  },
  {
    "external_url": "/product/15-6-noutbuk-lenovo-thinkbook-15-iil-20sm009mru-serebristyy-182539283/",
    "image_url": "https://cdn1.ozone.ru/s3/multimedia-t/wc250/6019822241.jpg",
    "name": "15.6\" Ноутбук Lenovo ThinkBook 15-IIL (20SM009MRU), серебристый",
    "price": 71118
  },
  {
    "external_url": "/context/detail/id/201066450/",
    "image_url": "https://cdn1.ozone.ru/s3/multimedia-3/wc250/6021280899.jpg",
    "name": "13.3\" Ноутбук HP EliteBook 735 G6 (6XE78EA), серебристый",
    "price": 93899
  },
  {
    "external_url": "/context/detail/id/204399189/",
    "image_url": "https://cdn1.ozone.ru/s3/multimedia-6/wc250/6022759422.jpg",
    "name": "17.3\" Ноутбук Lenovo IdeaPad 3-17 (81W2003WRK) (81W2003WRK), серый",
    "price": 50373
  },
  {
    "external_url": "/context/detail/id/204194561/",
    "image_url": "https://cdn1.ozone.ru/s3/multimedia-l/wc250/6019710561.jpg",
    "name": "13.5\" Ноутбук Acer Swift 3 SF313-52-71E9 (NX.HQWER.007), серебристый",
    "price": 82893
  },
  {
    "external_url": "/product/15-6-noutbuk-msi-gl65-10scsr-018ru-9s7-16u822-018-chernyy-189808008/",
    "image_url": "https://cdn1.ozone.ru/s3/multimedia-v/wc250/6015294199.jpg",
    "name": "15.6\" Ноутбук MSI GL65 10SCSR-018RU (9S7-16U822-018), черный",
    "price": 95590
  },
  {
    "external_url": "/product/igrovoy-noutbuk-15-6-lenovo-ideapad-l340-15irh-gaming-v-internet-magazine-ozon-tseny-otzyvy-172721696/",
    "image_url": "https://cdn1.ozone.ru/s3/multimedia-p/wc250/6003644593.jpg",
    "name": "15.6\" Игровой ноутбук Lenovo IdeaPad L340-15IRH Gaming (81LK00A3RK), черный",
    "price": 97990
  },
  {
    "external_url": "/product/noutbuk-14-lenovo-thinkpad-x1-carbon-7-20qd0033rt-v-internet-magazine-ozon-tseny-otzyvy-172476899/",
    "image_url": "https://cdn1.ozone.ru/s3/multimedia-9/wc250/6011352285.jpg",
    "name": "14\" Ноутбук Lenovo ThinkPad X1 Carbon 7 (20QD0033RT) (20QD0033RT), черный",
    "price": 133065
  },
  {
    "external_url": "/product/13-3-noutbuk-hp-elite-dragonfly-8mk76ea-siniy-189374204/",
    "image_url": "https://cdn1.ozone.ru/s3/multimedia-e/wc250/6006096902.jpg",
    "name": "13.3\" Ноутбук HP Elite Dragonfly (8MK76EA), синий",
    "price": 174290
  },
  {
    "external_url": "/context/detail/id/201066048/",
    "image_url": "https://cdn1.ozone.ru/s3/multimedia-8/wc250/6020590352.jpg",
    "name": "13.4\" Ноутбук Dell XPS 13 9300 (9300-3294), серебристый",
    "price": 160199
  },
  {
    "external_url": "/context/detail/id/201066019/",
    "image_url": "https://cdn1.ozone.ru/s3/multimedia-c/wc250/6021113472.jpg",
    "name": "13.3\" Ноутбук HP EliteBook x360 830 (7KP93EA), серебристый",
    "price": 137899
  },
  {
    "external_url": "/context/detail/id/204395884/",
    "image_url": "https://cdn1.ozone.ru/s3/multimedia-w/wc250/6027843476.jpg",
    "name": "14\" Ноутбук Dell Vostro 5401 (5401-2727) (5401-2727), серый",
    "price": 71360
  },
  {
    "external_url": "/context/detail/id/201066358/",
    "image_url": "https://cdn1.ozone.ru/s3/multimedia-2/wc250/6020600354.jpg",
    "name": "13.3\" Ноутбук HP EliteBook 830 G6 (7KP16EA), серебристый",
    "price": 108999
  },
  {
    "external_url": "/context/detail/id/204118298/",
    "image_url": "https://cdn1.ozone.ru/s3/multimedia-a/wc250/6027609598.jpg",
    "name": "15.6\" Игровой ноутбук HP Pavilion Gaming 15-dk1045ur (22N35EA), черный",
    "price": 102109
  },
  {
    "external_url": "/context/detail/id/204399171/",
    "image_url": "https://cdn1.ozone.ru/s3/multimedia-l/wc250/6027844977.jpg",
    "name": "15.6\" Ноутбук Acer Aspire A515-55G-52ZS (NX.HZBER.001), черный",
    "price": 75480
  },
  {
    "external_url": "/product/13-3-noutbuk-hp-elitebook-735-g6-2-6xe79ea-serebristyy-186535805/",
    "image_url": "https://cdn1.ozone.ru/s3/multimedia-0/wc250/6020603232.jpg",
    "name": "13.3\" Ноутбук HP EliteBook 735 G6 (6XE79EA), серебристый",
    "price": 113890
  },
  {
    "external_url": "/product/15-6-noutbuk-lenovo-ideapad-s145-15api-81ut00l4ru-seryy-204991539/",
    "image_url": "https://cdn1.ozone.ru/s3/multimedia-j/wc250/6027985195.jpg",
    "name": "15.6\" Ноутбук Lenovo IdeaPad S145-15API (81UT00L4RU), серый",
    "price": 34465
  },
  {
    "external_url": "/context/detail/id/200463219/",
    "image_url": "https://cdn1.ozone.ru/s3/multimedia-4/wc250/6019024348.jpg",
    "name": "14\" Ноутбук Acer TravelMate P2 TMP214-52-54ZR (NX.VLHER.00U), черный",
    "price": 92190
  },
  {
    "external_url": "/product/noutbuk-14-lenovo-thinkpad-x1-carbon-7th-gen-20qd00m4rt-v-internet-magazine-ozon-tseny-otzyvy-172721531/",
    "image_url": "https://cdn1.ozone.ru/s3/multimedia-3/wc250/6010387335.jpg",
    "name": "14\" Ноутбук Lenovo ThinkPad X1 Carbon (Gen 7) (20QD00M4RT), черный",
    "price": 184890
  },
  {
    "external_url": "/product/14-noutbuk-acer-travelmate-p6-tmp614-51t-g2-70r6-nx-vmter-008-chernyy-184487695/",
    "image_url": "https://cdn1.ozone.ru/s3/multimedia-z/wc250/6019898495.jpg",
    "name": "14\" Ноутбук Acer TravelMate P6 TMP614-51T-G2-70R6 (NX.VMTER.008), черный",
    "price": 162890
  },
  {
    "external_url": "/context/detail/id/201066000/",
    "image_url": "https://cdn1.ozone.ru/s3/multimedia-g/wc250/6022883956.jpg",
    "name": "13.3\" Ноутбук HP EliteBook x360 1030 G4 (7YL38EA), серебристый",
    "price": 129190
  },
  {
    "external_url": "/product/14-noutbuk-acer-travelmate-p6-tmp614-51t-g2-50lf-nx-vmrer-004-chernyy-184487693/",
    "image_url": "https://cdn1.ozone.ru/s3/multimedia-y/wc250/6019898494.jpg",
    "name": "14\" Ноутбук Acer TravelMate P6 TMP614-51T-G2-50LF (NX.VMRER.004), черный",
    "price": 134890
  },
  {
    "external_url": "/context/detail/id/193951019/",
    "image_url": "https://cdn1.ozone.ru/s3/multimedia-r/wc250/6022679379.jpg",
    "name": "15.6\" Ноутбук Lenovo ThinkBook 15-IIL (20SM003VPB), серый",
    "price": 84411
  },
  {
    "external_url": "/context/detail/id/193951005/",
    "image_url": "https://cdn1.ozone.ru/s3/multimedia-9/wc250/6022679361.jpg",
    "name": "13.3\" Ноутбук HP ProBook 430 G7 (8VU53EA), серебристый",
    "price": 73102
  },
  {
    "external_url": "/product/13-3-noutbuk-microsoft-surface-3-chernyy-181055933/",
    "image_url": "https://cdn1.ozone.ru/s3/multimedia-v/wc250/6018554287.jpg",
    "name": "13.3\" Ноутбук Microsoft Surface 3, черный",
    "price": 141188
  },
  {
    "external_url": "/context/detail/id/194417075/",
    "image_url": "https://cdn1.ozone.ru/s3/multimedia-e/wc250/6022679366.jpg",
    "name": "15.6\" Ноутбук Fujitsu LifeBook E559 (LKN:E5590M0006PL), черный",
    "price": 105145
  },
  {
    "external_url": "/product/13-3-noutbuk-hp-elitebook-830-g7-176x8ea-serebristyy-193950927/",
    "image_url": "https://cdn1.ozone.ru/s3/multimedia-2/wc250/6022679390.jpg",
    "name": "13.3\" Ноутбук HP EliteBook 830 G7 (176X8EA), серебристый",
    "price": 116475
  },
  {
    "external_url": "/context/detail/id/193950534/",
    "image_url": "https://cdn1.ozone.ru/s3/multimedia-c/wc250/6022679328.jpg",
    "name": "14\" Ноутбук HP EliteBook 840 G7 (176X7EA), черный, серебристый",
    "price": 125038
  },
  {
    "external_url": "/product/noutbuk-lenovo-gaming-3-15imh05-81y4006vru-siniy-hameleon-182449869/",
    "image_url": "https://cdn1.ozone.ru/s3/multimedia-q/wc250/6015833726.jpg",
    "name": "15.6\" Ноутбук Lenovo IdeaPad Gaming 3 15IMH05 (81Y4006VRU), синий",
    "price": 77950
  },
  {
    "external_url": "/product/15-6-igrovoy-noutbuk-asus-rog-zephyrus-g15-ga502iu-hn098-90nr03v1-m02410-chernyy-188486314/",
    "image_url": "https://cdn1.ozone.ru/s3/multimedia-v/wc250/6021198955.jpg",
    "name": "15.6\" Игровой ноутбук ASUS ROG Zephyrus G15 GA502IU-HN098 (90NR03V1-M02410), черный",
    "price": 102841
  },
  {
    "external_url": "/product/noutbuk-ip-5-15are05-81yq0018rk-182449878/",
    "image_url": "https://cdn1.ozone.ru/s3/multimedia-l/wc250/6027153885.jpg",
    "name": "15.6\" Ноутбук Lenovo IdeaPad 5 15ARE05 (81YQ0018RK), бирюзовый",
    "price": 57113
  },
  {
    "external_url": "/product/15-6-noutbuk-xiaomi-mi-notebook-pro-seryy-182133822/",
    "image_url": "https://cdn1.ozone.ru/s3/multimedia-q/wc250/6019065266.jpg",
    "name": "15.6\" Ноутбук Xiaomi Mi Notebook Pro, серый",
    "price": 99990
  },
  {
    "external_url": "/context/detail/id/160716340/",
    "image_url": "https://cdn1.ozone.ru/s3/multimedia-x/wc250/6027153753.jpg",
    "name": "15.6\" Ноутбук Acer Aspire A315-42G-R4CM (NX.HF8ER.02G), черный",
    "price": 40890
  },
  {
    "external_url": "/product/15-6-noutbuk-lenovo-ideapad-5-15iil05-81yk001frk-seryy-175414771/",
    "image_url": "https://cdn1.ozone.ru/s3/multimedia-g/wc250/6028164688.jpg",
    "name": "15.6\" Ноутбук Lenovo IdeaPad 5 15IIL05 (81YK001FRK), серый",
    "price": 50328
  },
  {
    "external_url": "/product/15-6-noutbuk-asus-x512da-bq1191t-90nb0lz3-m21300-seryy-182438935/",
    "image_url": "https://cdn1.ozone.ru/s3/multimedia-i/wc250/6027153846.jpg",
    "name": "15.6\" Ноутбук ASUS X512DA-BQ1191T (90NB0LZ3-M21300), серый",
    "price": 45628
  },
  {
    "external_url": "/product/15-6-igrovoy-noutbuk-hp-pavilion-gaming-15-dk1004ur-103r6ea-chernyy-179266534/",
    "image_url": "https://cdn1.ozone.ru/s3/multimedia-1/wc250/6017712001.jpg",
    "name": "15.6\" Игровой ноутбук HP Pavilion Gaming 15-dk1004ur (103R6EA), черный",
    "price": 84624
  },
  {
    "external_url": "/product/15-6-noutbuk-msi-gl65-10scsr-020xru-9s7-16u822-020-chernyy-181895942/",
    "image_url": "https://cdn1.ozone.ru/s3/multimedia-a/wc250/6025828678.jpg",
    "name": "15.6\" Ноутбук MSI GL65 10SCSR-020XRU (9S7-16U822-020), черный",
    "price": 77989
  },
  {
    "external_url": "/context/detail/id/201849252/",
    "image_url": "https://cdn1.ozone.ru/s3/multimedia-y/wc250/6022068754.jpg",
    "name": "14\" Ноутбук HP ProBook 445 G7 (1F3K8EA), серебристый",
    "price": 63800
  }
]